Workbook

Sheet RATIO
K2: Standort | L2: (Alle)
K3: Verantwortlich | L3: (Alle)
K5: Count | L5: Prio
K6: Zeilenbeschriftungen | L6: Hoch | M6: Mittel | N6: Kritisch | O6: Niedrig | P6: (Leer) | Q6: Gesamtergebnis
K7: Offen | L7: 35 | M7: 17 | N7: 2 | O7: 1 | P7: 2 | Q7: 57
K8: Major NC | L8: 9 | M8: 1 | N8: 2 | Q8: 12
K9: Minor NC | L9: 15 | M9: 14 | P9: 1 | Q9: 30
K10: Observation | L10: 10 | M10: 2 | O10: 1 | P10: 1 | Q10: 14
K11: (Leer) | L11: 1 | Q11: 1
K12: (Leer) | L12: 1 | P12: 1 | Q12: 2
K13: Major NC | L13: 1 | Q13: 1
K14: Observation | P14: 1 | Q14: 1
K15: In Bearbeitung | L15: 2 | Q15: 2
K16: Minor NC | L16: 2 | Q16: 2
K17: Gesamtergebnis | L17: 38 | M17: 17 | N17: 2 | O17: 1 | P17: 3 | Q17: 61

Sheet TISAX Finding Register
A1: Finding-ID | B1: ISA Modul | C1: Kapitel | D1: Kontroll-Nr. | E1: Kontrollfrage (EN) | F1: Kontrollfrage (DE) | G1: Finding-Typ | H1: Finding-Beschreibung | I1: Reifegrad IST (0-5) | J1: Reifegrad SOLL | K1: Gap | L1: Maßnahme | M1: Umsetzungsgegenstand, Prozessbezug und Workflow Items | N1: X-Referenzen zu StageReview Findings | O1: Complete Remediation Scope | P1: Verantwortlich | Q1: Standort | R1: Priorität | S1: Status | T1: Frist | U1: Nachweis / Link | V1: ISB-Kommentar | W1: Ct.
A2: F-General | B2: General Evidence in Catalogue | C2: General | E2: Automotive treatment by OEM | F2: Automotive treatment by OEM | G2: Observation | H2: Die OEM´s versuchen Ihre Lieferanten auszusortieren, über diesen (TISAX) Vorwand, kommt auf die Auswahl an alternativen Lieferanten an. Wenn Preis gleich ist oder wenn ersetzbar. Wenn schwer ersatzbar dann ist TISAX wieder wichtig. | K2: =IF(AND(ISNUMBER(I2),ISNUMBER(J2)),J2-I2,"") | L2: Awareness Sales und KAMs | M2: Umsetzungsgegenstand: Awareness Sales und KAMs | N2: Vorgelagert (Voraussetzung): - keine (eigenständige Lessons-Learned-Auswertung) Nachgelagert (liefert Input an): - Row 31 / F-013 / 1.6.1 (Incident Meldewesen) - Row 33 / F-015 / 1.6.3 (Krisen-/BCM) - Row 49 / F-031 / 5.2.3 (Malware-Schutz) - Row 50 / F-032 / 5.2.4 (Logging/Eventprot.) - Row 54 / F-036 / 5.2.8 (BCM/DR-Tests) Querverweise: - Row 32 / F-014 / 1.6.2 (OEM-Kommunikation) - Row 6 / F-General/Major NC (Wirksamkeit ML3) | P2: Sales Hubertus Linz | Q2: Alle | R2: Mittel | S2: Offen | T2: 46142 | W2: 1
A3: F-General | B3: General Evidence in Catalogue | C3: Row "E" more details for the "how" of the implementation description | E3: To what extent are information security policies available? | F3: Inwieweit sind Informationssicherheitsrichtlinien verfügbar? | G3: Observation | H3: Row E to be extended | K3: =IF(AND(ISNUMBER(I3),ISNUMBER(J3)),J3-I3,"") | L3: Klare Definition Richtlinie zur Dokumentenlenkung, Terminologie für Dateinamen, wer ist verantwortlich für Richtlinie (Einkauf, IT, etc.) -> Dokumentenlenkungsrichtlinie Überprüfungsdatum muss ersichtlich sein. Ist der Verantwortliche sichtbar im BOS. Vorlage für Policy. -> Wie werden Richtlinien erstellt , wer die Verantwortung dafür hat, Namenskonventionen und Freigabeprozess. -> Prüfung ob der Prozess- bzw. Dokumentenverantwortliche im BOS genannt und ersichtlich ist. -> Prozess wie BOS sich verhält, wenn der jährliche Review nicht erfolgt ist (Policy Bestandteil). | M3: Umsetzungsgegenstand: Verbindliche Dokumentenlenkungsrichtlinie als Top-Level-Vorgabe für das gesamte ISMS-Policy-Framework (Namenskonvention, Versionierung, Approval, Review-Zyklus, Eigentümer/Reviewer). Prozessbezug: VDA ISA 1.1.1; ISO 27001 Clause 7.5 (dokumentierte Information); BOS/ISM in QBD.net. Workflow Items: 1. Erstellung Richtlinie Dokumentenlenkung (Owner: ISB) inkl. Klassifizierungsfeld und 12-Monats-Review. 2. BOS-Steckbrief je Policy mit sichtbarem Dokumenten- und Prozessverantwortlichen. 3. BOS-Eskalations-Workflow bei nicht erfolgtem Jahres-Review. Nachweis: Richtlinie freigegeben, Stichprobe Policy-Liste mit Reviewdatum, BOS-Reportauszug. Abhängigkeiten (Detail s. Spalte N): → methodisches Cross-Cutting für alle Findings | N3: Vorgelagert: - keine (methodisches Catalogue-Finding) Nachgelagert: - ALLE Findings (Catalogue-Pflege betrifft alle Module) Querverweise: - Row 4 / F-General (Unternehmensgrößen-Anpassung) - Row 5 / F-General (Catalogue Row F) | O3: Policy Framework: - ISMS-Dokumentenstrategie (Master-Dokumentenliste) Standards/Leitfäden: - VDA ISA 6.0.3 Anwendungsleitfaden (ENX) - ENX Assessment Guidance (aktuelle Version) Weitere Empfehlungen: - Catalogue-Pflege-Prozess als Audit-Pre-Check etablieren - Nachweispfade zentral in ISMS-Tool (z. B. SharePoint-Library) referenzieren - Auditor-Kommunikation: Catalogue-Updates protokollieren | P3: Roland Walter | Q3: Alle | R3: Hoch | S3: Offen | T3: 46142 | W3: 1
A4: F-General | B4: General Evidence in Catalogue | C4: General | E4: Unternehmensgrößen irrelevant | F4: Dem Unternehmen angemessen” gibt es nicht. | G4: Observation | H4: Unternehmensgröße wird nicht berücksichtigt. Wenn du AL3 willst musst du die Kontrollfragen beantworten. “ | L4: Keine Ausnahmen bei Wirksamkeitsnachweisen aufgrund Belegschaftsgröße bzw. Unternehmensgröße. | M4: Umsetzungsgegenstand: Verzicht auf Ausnahme-Argumentation aufgrund Unternehmensgröße; vollständige Erfüllung aller VDA-ISA-Kontrollen im AL3-Scope mit dokumentierter Risiko-Begründung bei Nicht-Anwendbarkeit. Prozessbezug: VDA ISA 6.0.3 Methodik AL3; ENX-Prüfvorgaben; SoA-Logik ISO 27001 Clause 6.1.3. Workflow Items: 1. SoA-Review (Owner: ISB): jede 'n/a'-Markierung mit dokumentierter Risikobegründung. 2. Briefing aller Maßnahmenverantwortlichen: keine Größenargumente in Auditgesprächen. Nachweis: SoA mit vollständiger Begründungstabelle, Trainingsnachweis. Abhängigkeiten (Detail s. Spalte N): → definiert AL3-Niveau für ALLE Findings | N4: Vorgelagert: - keine Nachgelagert: - ALLE Findings mit AL3-Reifegrad-Erwartung (Ist-Bewertung) | O4: Policy Framework: - Statement of Applicability (SoA) mit AL3-Begründung je Control - ISMS-Scope-Dokument inkl. Unternehmensgrößen-Argumentation Standards: - VDA ISA 6.0.3 Maturity Model (ML 0–5) - ENX Simplified Group Assessment (SGA) Guidance - ISO/IEC 27001:2022 §4.3 Scope Weitere Empfehlungen: - Hybrid-Assessment-Strategie (SGA + individuell) dokumentieren - Maturity-Gap-Analyse je Standort mit Ziel ML 2,5 - Auditor-Frühabstimmung zur AL3-Erwartungshaltung pro Werk | P4: Alle | Q4: Alle | R4: Hoch
A5: F-General | B5: Catalogue Row F | C5: Row "F" must include document name, version and date. | E5: To what extent are information security policies available? | F5: Inwieweit sind Informationssicherheitsrichtlinien verfügbar? | G5: Observation | H5: Row "F" must include document name, version and date. | J5: 3 | L5: Bei F darauf achten das die Version und den Dokumentennamen + Datum in der excel ersichtlich ist | M5: Umsetzungsgegenstand: Sicherstellung, dass in der ISA-Excel (Spalte F – Implementation) zu jeder Kontrolle Dokumentname, Versionsnummer und Datum vollständig benannt sind. Prozessbezug: VDA ISA 6.0.3 Antwortmethodik (Catalogue Row F); ENX-Audit-Format. Workflow Items: 1. ISA-Excel pro Standort prüfen (Owner: ISB), Vollständigkeit Dokname/Version/Datum. 2. Standardformatvorgabe an alle Verantwortlichen kommunizieren. Nachweis: vollständig befüllte ISA-Spalte F, Stichprobenprotokoll. Abhängigkeiten (Detail s. Spalte N): → baut auf F-001/1.1.1; betrifft Spalte S aller Findings | N5: Vorgelagert: - Row 7 / F-001 / 1.1.1 (Dokumentenlenkungs-RL liefert Versionierung) Nachgelagert: - ALLE Findings (Spalte S Nachweis/Link muss Dokumentenkopf erfüllen) | O5: Policy Framework: - RL Dokumentenlenkung mit verpflichtenden Metadaten (Name, Version, Datum, Klassifikation, Eigentümer) - Dokumentenkopf-Vorlage (REUTIB-Corporate-Design) Standards: - ISO/IEC 27001:2022 A.5.1, A.5.37 - ISO 9001:2015 §7.5 (Dokumentierte Information) - VDA ISA 6.0.3 Kap. 1.1.1 Weitere Empfehlungen: - Document-Owner-Liste mit Review-Zyklus im ISMS-Tool - Catalogue-Audit: Stichprobe 20 % aller Policies pro Quartal | W5: 1
A6: F-General | B6: Control Verification | C6: All Kapitel | E6: To what extent are information security policies available? | F6: Inwieweit sind Informationssicherheitsrichtlinien verfügbar? | G6: Major NC | H6: Implementation of workflows and evidences of training and enforcements | J6: 3 | L6: No Training, no enforcement of process according to control no Maturity Level 3 | M6: Umsetzungsgegenstand: Aufbau eines verbindlichen Trainings- und Enforcement-Verfahrens je Richtlinie/Standard als Kern-AL3-Voraussetzung — Reifegrad 3 setzt dokumentierte und nachweisbare Durchsetzung voraus. Prozessbezug: VDA ISA-Reifegradlogik (Level 3 'etabliert'); ISO 27001 Clause 7.2/7.3; VDA ISA 2.1.3 (Awareness & Training). Workflow Items: 1. Verknüpfung TTT-Konzept mit Policy-Framework (Owner: ISB + HR). 2. Schulungsmatrix Richtlinie × Zielgruppe × Standort × Sprache. 3. Wirksamkeits-Stichproben (Phishing-Simulation, Walkthrough-Tests). 4. Internes Auditprogramm integriert. Nachweis: Trainingsregister je MA, Stichprobenprotokoll, Audit-Berichte. Abhängigkeiten (Detail s. Spalte N): → zwingend vor ML3: F-001, F-002, F-011, F-018 | N6: Vorgelagert (zwingend für ML3): - Row 7-9 / F-001 / 1.1.1 (Policy Framework) - Row 29 / F-011 / 1.5.1 (KPIs / Wirksamkeit) - Row 12 / F-002 / 1.2.1 (KPI-Definition) Nachgelagert: - Row 36 / F-018 / 2.1.3 (TTT-Schulungskonzept) - ALLE Findings (Workflow-Nachweise pro Owner) Querverweise: - Row 4 / F-General (AL3-Niveau) - Row 30 / F-012 / 1.5.2 (Independent Review) | O6: Policy Framework: - Master-Schulungs- und Awareness-Konzept (TTT) - RL Wirksamkeitsmessung & ISMS-KPIs - Approval-Workflow-Matrix (RACI je Prozess) Standards: - ISO/IEC 27001:2022 §7.2 (Kompetenz), §7.3 (Awareness), §9.1 (Monitoring) - ISO/IEC 27004 (ISMS-Metriken) - VDA ISA 6.0.3 Kap. 1.5.1 (Wirksamkeit) Regulatorisch: - NIS-2 Art. 20(2) Schulungspflicht Leitung - NIS-2 Art. 21(2)(g) Cyberhygiene & Schulung Weitere Empfehlungen: - Vor AL3-Hauptaudit: Workflow-Walkthrough mit allen Process Ownern - Trainings-KPI: Abdeckungsgrad ≥ 95 % je Standort - TTT-C-Level-Approval-Meeting (30 Min) priorisieren — Vorbedingung für ML3 | Q6: Alle | R6: Hoch | W6: 1
A7: F-001 | B7: Information Security | C7: IS Policies and Organization | D7: 1.1.1 | E7: To what extent are information security policies available? | F7: Inwieweit sind Informationssicherheitsrichtlinien verfügbar? | G7: Minor NC | H7: Anforderung Erstellung BOS/ISM Dokumentenlenkungsrichtlinie | I7: 2 | J7: 3 | K7: =IF(AND(ISNUMBER(I7),ISNUMBER(J7)),J7-I7,"") -> 1 | L7: Erstellung einer Richtlinie zur Dokumentenlenkung im CAQ QBD.net (BOS/ISM), inklusive Terminologie für Dateinamen, wie auch der Regelungen der Verantwortlichkeiten im BOS/ISM Kontext, | M7: Umsetzungsgegenstand: Dokumentenlenkungsrichtlinie für BOS/ISM-Dokumente in CAQ QBD.net (Namenskonvention, Klassifizierung, Approval, Review, Archivierung). Prozessbezug: VDA ISA 1.1.1; ISO 27001 A.5.1 + Clause 7.5; BOS/ISM-Governance. Workflow Items: 1. RL-Entwurf (Owner: ISB). 2. Review im BOS/ISMS-Coordination-Meeting. 3. Freigabe GL. 4. Roll-out + Awareness DE/AT/SK/PL. Nachweis: RL v1.0 in QBD.net, Trainingsnachweis, BOS-Eintrag. Abhängigkeiten (Detail s. Spalte N): → Fundament: Voraussetzung für ALLE Policy-Findings | N7: Vorgelagert: - keine (Fundamentbaustein) Nachgelagert (Voraussetzung für): Gegenprüfung für Anwendbarkeit und Verantwortung benannter QS-Engineers bzw. Responsbies in den Standorten. | O7: Policy Framework: - Master-RL Dokumentenlenkung BOS/ISMS - Verbindliche Metadaten: Titel, Version, Datum, Owner, Klassifikation, Freigabe - Dokumentenstruktur-Pyramide (RL → Verfahrensanweisung → Arbeitsanweisung → Formular) Standards: - ISO/IEC 27001:2022 A.5.1, A.5.37 - ISO 9001:2015 §7.5 - VDA ISA 6.0.3 Kap. 1.1.1 Weitere Empfehlungen: - Dokumentenmanagementsystem (z. B. SharePoint/M-Files) als Single Source - Versionshistorie & Approval-Workflow elektronisch (revisionssicher) - 4-sprachige Verfügbarkeit DE/EN/SK/PL für relevante Top-Level-RL | P7: Roland Walter | Q7: Alle | R7: Hoch | S7: In Bearbeitung | T7: 46142 | W7: 1
A8: F-001 | B8: Information Security | C8: IS Policies and Organization | D8: 1.1.1 | E8: To what extent are information security policies available? | F8: Inwieweit sind Informationssicherheitsrichtlinien verfügbar? | G8: Minor NC | H8: Überprüfungsdatum muss ersichtlich sein | I8: 2 | J8: 3 | K8: =IF(AND(ISNUMBER(I8),ISNUMBER(J8)),J8-I8,"") -> 1 | L8: Nachprüfung und Ergänzung Reviewdatum muss in der Policy nach Approval sichtbar sein. | M8: Umsetzungsgegenstand: Sichtbarmachung des Review- und Approval-Datums in der Kopfzeile jeder Policy nach Freigabe. Prozessbezug: VDA ISA 1.1.1; Dokumentenlenkungsrichtlinie (Bezug F-001/Row 7). Workflow Items: 1. Policy-Template anpassen (Felder: letzte Review, nächste Review, Approver, Approval-Datum) — Owner: ISB. 2. Nacharbeit aller Bestandsdokumente. 3. BOS-Reporting Liste aller RL mit Review-Daten. Nachweis: Sample-Audit 5 RL, BOS-Reportauszug. Abhängigkeiten (Detail s. Spalte N): → baut auf F-001/1.1.1 | N8: Vorgelagert: - Row 7 / F-001 / 1.1.1 (Dokumentenlenkungs-RL) Nachgelagert: - ALLE Policies/Verfahrensanweisungen (Review-Pflicht) Querverweise: - Row 5 / F-General (Catalogue-Metadaten) | O8: Policy Framework: - Review-Zyklen-Matrix: Top-Level-RL jährlich, Verfahrensanweisungen 2-jährlich, anlassbezogen ad hoc - Review-Trigger: Gesetzesänderung, Vorfall, Audit-Finding, Org-Änderung Standards: - ISO/IEC 27001:2022 A.5.1.2 (Review of policies) - ISO 9001:2015 §7.5.3 Weitere Empfehlungen: - Automatisierte Erinnerungen 60/30/14 Tage vor Review-Datum - Review-Protokoll als Pflichtnachweis (auch bei 'no changes') - Quartalsbericht 'überfällige Reviews' an CIO/Geschäftsleitung | P8: Mark Lütz | Q8: Alle | R8: Hoch | S8: In Bearbeitung | T8: 46142 | W8: 1
A9: F-001 | B9: Information Security | C9: IS Policies and Organization | D9: 1.1.1 | E9: To what extent are information security policies available? | F9: Inwieweit sind Informationssicherheitsrichtlinien verfügbar? | G9: Minor NC | H9: Alle Policies in der Klassifizierung auf "Intern" umstellen. | I9: 2 | J9: 3 | K9: =IF(AND(ISNUMBER(I9),ISNUMBER(J9)),J9-I9,"") -> 1 | L9: Umstellung Klassifizierung auf "Intern". | M9: Umsetzungsgegenstand: Vereinheitlichung der Dokumentenklassifizierung aller internen Richtlinien auf 'Intern' gem. Klassifizierungsschema. Prozessbezug: VDA ISA 1.1.1; Asset-Mgmt.- und Klassifizierungs-Policy; ISO 27001 A.5.12/A.5.13. Workflow Items: 1. Bestandsaufnahme aller Policies (Owner: ISB) und Klassifizierungsstatus. 2. Bulk-Anpassung Klassifizierung 'Intern' in QBD.net. 3. Aktualisierung Template-Standard. Nachweis: Klassifizierungs-Auditliste, QBD.net-Reportauszug. Abhängigkeiten (Detail s. Spalte N): → baut auf F-001 + F-010; nachgelagert F-028 | N9: Vorgelagert: - Row 7 / F-001 / 1.1.1 (Dokumentenlenkungs-RL) - Row 28 / F-010 / 1.4.1 (Klassifizierungsschema) Nachgelagert: - ALLE Policies (einheitliche Klassifikation) - Row 46 / F-028 / 5.1.2 (Verschlüsselung je Klasse) Querverweise: - Row 42 / F-024 / 4.1.2 (MFA je Klassifikation) | O9: Policy Framework: - RL Informationsklassifizierung mit 4 Stufen: Öffentlich / Intern / Vertraulich / Streng vertraulich - OEM-spezifisches Mapping ('Strictly Confidential' = Streng vertraulich) Standards: - ISO/IEC 27001:2022 A.5.12, A.5.13 - VDA ISA 6.0.3 Kap. 1.4.1 - VDA Prototypenschutz-Leitfaden Weitere Empfehlungen: - Dokumentenkopf-Vorlage mit Klassifikations-Stempel - DLP-Policy verknüpft mit Klassifikation (M365 Sensitivity Labels) - Schulungs-Modul Klassifikation als Pflichtschulung (TTT-Phase 2) | P9: Mark Lütz | Q9: Alle | R9: Hoch | S9: Offen | T9: 46142 | W9: 1
A10: F-002 | B10: Information Security | C10: IS Policies and Organization | D10: 1.2.1 | E10: To what extent is information security managed within the organization? | F10: Inwieweit wird die Informationssicherheit innerhalb der Organisation verwaltet? | G10: Major NC | H10: Security Incident Response Mgmt. | I10: 2 | J10: 3 | K10: =IF(AND(ISNUMBER(I10),ISNUMBER(J10)),J10-I10,"") -> 1 | L10: Was sind "Safety & Security Vorfälle", aktuell gibt es keine Beschreibung. Aufnahme Meldekette und entspr. Saftey & Sec. Incident Mailbox. Anpassung PROC für Prozessimplementierung, POL anpassen (inkl. Beispiele), Guideline aufbauen und STD für die entspr. Bereiche, inkl. Trainings in den Sprachversionen. | M10: Umsetzungsgegenstand: Vollständige Etablierung Information-Security-Incident-Response: Definition Sicherheitsereignis vs. Sicherheitsvorfall, Meldekette, zentrale Mailbox, Sprachversionen, Trainings. Prozessbezug: VDA ISA 1.2.1 + 1.6.1/1.6.2; ISO 27001 A.5.24–A.5.28; NIS-2 Art. 23 (Meldepflichten). Workflow Items: 1. RL Incident Response (Owner: ISB) mit definierten Begriffen. 2. Aufbau STD Meldekette + zentrale Mailbox security-incident@reutib.com. 3. PROC-Anpassung für IT/OT/Facility/Krisenstab. 4. Trainings DE/EN/SK/PL inkl. OT-Schichtleiter. Nachweis: RL/STD/PROC freigegeben, Trainingsnachweise, Live-Tickets als Wirksamkeit. Abhängigkeiten (Detail s. Spalte N): → Major NC; baut auf F-001 + F-010; treibt F-013/F-014/F-015 | N10: Vorgelagert: - Row 7 / F-001 / 1.1.1 (Doku-Lenkung) - Row 28 / F-010 / 1.4.1 (Risiko-Framework) Nachgelagert (entfaltet sich in): - Row 31 / F-013 / 1.6.1 (Incident Meldewesen) - Row 32 / F-014 / 1.6.2 (OEM-Kommunikation) - Row 33 / F-015 / 1.6.3 (Krise/BCM) Querverweise: - Row 2 / F-General (Play-Ransomware Lessons-Learned) - Row 49 / F-031 / 5.2.3 (Malware) - Row 50 / F-032 / 5.2.4 (Logging als Detektion) | O10: Policy Framework: - RL Incident Response & Security Operations - IR-Playbooks (Ransomware, Phishing, Data Breach, OT-Incident) - SOC-Runbook für 24/7-Reaktion (extern oder intern) Standards: - ISO/IEC 27001:2022 A.5.24-A.5.28 - ISO/IEC 27035-1/-2 (Incident Mgmt Lifecycle) - NIST SP 800-61r2 (Computer Security Incident Handling) - VDA ISA 6.0.3 Kap. 1.2.1 / 1.6.x Regulatorisch: - NIS-2 Art. 21(2)(c), Art. 23 (Meldepflicht) - DSGVO Art. 33, 34 (Datenschutzvorfälle) Weitere Empfehlungen: - Major NC: Vorbereitung Wirksamkeitsnachweis mit Sophos-XDR-Auswertung - Eskalations-Matrix mit OEM-Kontakten je Werk - Tabletop-Übung 2026 vor Hauptaudit | P10: ISB, IT, GL | Q10: Alle | R10: Hoch | S10: Offen | T10: 46157 | W10: 1
A11: F-002 | B11: Information Security | C11: IS Policies and Organization | D11: 1.2.1 | E11: To what extent is information security managed within the organization? | F11: Inwieweit wird die Informationssicherheit innerhalb der Organisation verwaltet? | G11: Major NC | H11: Audit Programm u. Verantwortlichkeiten fehlen. | I11: 2 | J11: 3 | K11: =IF(AND(ISNUMBER(I11),ISNUMBER(J11)),J11-I11,"") -> 1 | L11: Internes Auditprogramm, wann , wer und wo definiert. | M11: Umsetzungsgegenstand: Internes ISMS-Auditprogramm (3-Jahres-Plan) mit definierten Auditzeitpunkten, Auditorenpool, Auditbereichen und Berichtswesen. Prozessbezug: VDA ISA 1.2.1 + 1.5.2; ISO 27001 Clause 9.2. Workflow Items: 1. 3-Jahres-Auditplan (Owner: ISB). 2. Auditorenpool (intern + unabhängig) etablieren. 3. Audit-Programm-Richtlinie freigeben (GL). 4. Erste interne Audits DE-Leutenbach und AT-Bischofshofen. Nachweis: Auditplan, Auditberichte, Management-Review-Input. Abhängigkeiten (Detail s. Spalte N): → Major NC; liefert Input an F-011 (1.5.1) und F-012 (1.5.2) | N11: Vorgelagert: - Row 7 / F-001 / 1.1.1 (Doku-Lenkung) - Row 16 / F-003 / 1.2.2 (ISB-Organigramm) Nachgelagert: - Row 29 / F-011 / 1.5.1 (Wirksamkeitsnachweise) - Row 30 / F-012 / 1.5.2 (Independent ISMS Review) - Row 50 / F-032 / 5.2.4 (Logging als Audit-Quelle) Querverweise: - Row 12 / F-002 / 1.2.1 (KPIs) | O11: Policy Framework: - RL Internes Audit & Management Review - Jahres-Auditprogramm 2026/2027 (rollierender 3-Jahres-Plan) - Audit-Charter (Unabhängigkeit, Berichtsweg an Geschäftsleitung) Standards: - ISO/IEC 27001:2022 §9.2 (Internal Audit), §9.3 (Management Review) - ISO 19011:2018 (Audit-Leitfaden) - VDA ISA 6.0.3 Kap. 1.2.1 Weitere Empfehlungen: - Lead Auditor-Qualifikation für 1 Person je Standort - Audit-Plan inkl. OT-Werke SK/PL/AT mit IEC-62443-Fokus - Audit-Findings-Tracker mit CAPA-Workflow (PDCA) | P11: Mark Lütz | Q11: Alle | R11: Mittel | S11: Offen | T11: 46157 | W11: 1
A12: F-002 | B12: Information Security | C12: IS Policies and Organization | D12: 1.2.1 | E12: To what extent is information security managed within the organization? | F12: Inwieweit wird die Informationssicherheit innerhalb der Organisation verwaltet? | G12: Minor NC | H12: Fehlende KPIs, Bewertung in der Label Abhängigkeit wo für die Controls notwendig.Nachweis fehlt für Assessment bzgl. Anwendbarkeit der Labels. | I12: 2 | J12: 3 | K12: =IF(AND(ISNUMBER(I12),ISNUMBER(J12)),J12-I12,"") -> 1 | L12: Siehe ISMS Policy in Punkt 5.2 "Stelle mir dar, dass Du alle Control-No betrachtet hast bzgl. Confidentail u. Very High Availability, Wichtig !: Trennung von Scorecard. Scorecard link oder doc von Patrick G. an Mark -> Mark erarbeitet KPI Dashboard für ISMS, Erzeugung Assessment Dokuments in der jährlichen Betrachtung. | M12: Umsetzungsgegenstand: ISMS-KPI-/KRI-Dashboard mit expliziter Label-Abhängigkeit (Confidential, Very High Availability) und Nachweis vollständiger Kontrollbetrachtung im jährlichen Assessment. Prozessbezug: VDA ISA 1.2.1; ISO 27001 Clause 9.1; Scorecard-Ableitung (Patrick G. → Mark Lütz). Workflow Items: 1. KPI-Set definieren (Owner: ISB) — Awareness-Quote, MTTD/MTTR, Patch-Compliance, BCM-Testrate, Lieferantenbewertungs-Quote. 2. Assessment-Dokument pro Label (C / Very High A). 3. Jährliche Wirksamkeitsbewertung als ISMS-Audit-Eingangsdokument. Nachweis: KPI-Dashboard, Assessment-Dokument, Management-Review-Protokoll. Abhängigkeiten (Detail s. Spalte N): → baut auf F-002 (Audit); Voraussetzung für F-011/F-012 + alle KPI-basierten Findings | N12: Vorgelagert: - Row 11 / F-002 / 1.2.1 (Auditprogramm) - Row 4 / F-General (AL3-Niveau) Nachgelagert: - Row 29 / F-011 / 1.5.1 (Wirksamkeit benötigt KPIs) - Row 30 / F-012 / 1.5.2 (Review benötigt KPIs) - Row 36 / F-018 / 2.1.3 (Schulungs-KPIs) - Row 50 / F-032 / 5.2.4 (Logging-KPIs) - Row 51 / F-033 / 5.2.5 (Patch-KPIs) Querverweise: - Row 6 / F-General (Workflow-KPIs) | O12: Policy Framework: - RL Wirksamkeitsmessung & ISMS-Kennzahlen - KPI-Katalog je VDA-ISA-Kapitel (Label-spezifisch: IS / Prototyp / Personenbez.) - ISMS-Cockpit (Power BI / Excel-Dashboard) mit Monats-Reporting Standards: - ISO/IEC 27001:2022 §9.1 (Monitoring) - ISO/IEC 27004 (ISMS-Metriken) - VDA ISA 6.0.3 Kap. 1.5.1 (für ML3 verbindlich) Weitere Empfehlungen: - Mindest-KPI-Set: Patch-Compliance, MFA-Coverage, Schulungs-Abdeckung, MTTR, Phishing-Klickrate, Vendor-Risk-Score - Label-Anwendbarkeitsmatrix als Anhang zum SoA - Quartals-Reporting an Geschäftsleitung als Wirksamkeitsnachweis | P12: Mark Lütz | Q12: Alle | R12: Mittel | S12: Offen | T12: 46157 | W12: 1
A13: F-003 | B13: Information Security | C13: IS Policies and Organization | D13: 1.2.2 | E13: To what extent are information security responsibilities organized? | F13: Inwieweit sind Informationssicherheitsaufgaben organisiert? | G13: Minor NC | H13: Fehlende Verantwortlichkeiten in OT SK/PL und Qualitfikationsnachweise in OT/PROD. | I13: 2 | J13: 3 | K13: =IF(AND(ISNUMBER(I13),ISNUMBER(J13)),J13-I13,"") -> 1 | L13: Wie sind die Verantworlichkeiten und die Kenntnisstände in der Produktoin definiert? Gibt es ein Dokument wo auch patches updates im OT berreich definiert sind? . Produktionsupdates, sicherheitslücken, gibt es backups, wurde das getestet Direkte Darstellung der Verantwortlichkeiten, Dokument: OT Seite zwingend erweitern für Produktionslinien in SK/PL Empfehlung für Training: Vorfallsbezogen agieren in OT | M13: Umsetzungsgegenstand: Definition und Dokumentation der IS-Verantwortlichkeiten und Qualifikationen im OT/Produktionsbereich, insbesondere für SK (Myjava) und PL (Międzyrzecze Górne). Prozessbezug: VDA ISA 1.2.2; IEC 62443-2-1 (Organisation und Verantwortlichkeiten im IACS); ISO 27001 A.5.2/A.5.3. Workflow Items: 1. RACI-Matrix OT-IS pro Standort (Owner: ISB + Plant Manager). 2. HR-Qualifikationsmatrix erweitern um OT-IS-Kompetenzen. 3. Patching-/Update-Verantwortlichkeiten OT dokumentieren. 4. Vorfallsbezogenes OT-Training (Schichtebene). Nachweis: RACI je Plant, Qualifikationsnachweise, OT-Verantwortlich-keits-RL. Abhängigkeiten (Detail s. Spalte N): → baut auf F-003 (Organigramm); treibt OT-Findings SK/PL | N13: Vorgelagert: - Row 16 / F-003 / 1.2.2 (ISB-Organigramm) Nachgelagert: - Row 14 / F-003 / 1.2.2 (OT-Assetliste SK/PL) - Row 15 / F-003 / 1.2.2 (OT-Verträge) - Row 21 / F-005 / 1.2.4 (OLA IT/OT) - Row 26-27 / F-009 / 1.3.4 (OT-SW-Mgmt + IEC 62443) - ALLE OT-Findings (5.2.5, 5.2.6, 5.2.7) Querverweise: - Row 17 / F-003 / 1.2.2 (IS in Projekten — Major NC) | O13: Policy Framework: - RL Rollen & Verantwortlichkeiten (RACI-Matrix IT/OT/IS) - Stellenbeschreibung OT-Verantwortlicher je Werk - Schnittstellenbeschreibung IT ↔ OT ↔ Qualität Standards: - ISO/IEC 27001:2022 A.5.2 (Roles & Responsibilities) - IEC 62443-2-1 (Security Programm für OT-Asset-Owner) - VDA ISA 6.0.3 Kap. 1.2.2 Weitere Empfehlungen: - OT-Lead je Standort SK-Myjava / PL-Międzyrzecze nominieren - Quartals-Jour-Fixe IT/OT/IS-Triade - OT-Verantwortlichkeiten in lokalen Sprachen kommunizieren | P13: SK/PL, HR, GL, ISB, OT/PROD. | Q13: SK/PL | R13: Hoch | S13: Offen | T13: 46172 | W13: 1
A14: F-003 | B14: Information Security | C14: IS Policies and Organization | D14: 1.2.2 | E14: To what extent are information security responsibilities organized? | F14: Inwieweit sind Informationssicherheitsaufgaben organisiert? | G14: Minor NC | H14: Vorgegebene OT Assetliste SK/PL ist noch nicht ausgefüllt von MB/TD. Erweitern für Connectivity für IP-Traffic (warum, wohin, was, wer steuert)? | I14: 2 | J14: 3 | K14: =IF(AND(ISNUMBER(I14),ISNUMBER(J14)),J14-I14,"") -> 1 | L14: Vervollständigung OT Asseliste und Erweiterung um Connectivity | M14: Umsetzungsgegenstand: Vervollständigung der OT-Asset-Liste SK/PL inkl. IP-Connectivity-Attribute (Protokoll, Ziel, Owner, Steuerung, Klassifizierung). Prozessbezug: VDA ISA 1.2.2 + 1.3.1; IEC 62443-2-1 Asset Inventory; ISO 27001 A.5.9. Workflow Items: 1. Asset-Erhebung vor Ort (Owner: Plant Manager + OT-Lead SK/PL). 2. Schemaerweiterung: Protokoll, Ziel-IP, Owner, Klassifizierung, Patchstand. 3. Übernahme in Matrix42 oder dediziertes OT-Repository. Nachweis: Asset-Liste SK/PL vollständig, IP-Kommunikationsmatrix. Abhängigkeiten (Detail s. Spalte N): → baut auf F-003; Pflicht für SK/PL; treibt OT-Findings 5.2.x | N14: Vorgelagert: - Row 13 / F-003 / 1.2.2 (OT-Verantwortlichkeiten) - Row 23 / F-006 / 1.3.1 (Asset Mgmt-Methodik) Nachgelagert: - Row 51 / F-033 / 5.2.5 (OT-Vulnerability Mgmt) - Row 52 / F-034 / 5.2.6 (OT-Pentest) - Row 53 / F-035 / 5.2.7 (OT-Netzwerk-Zonierung) - Row 55 / F-037 / 5.2.9 (OT-Backup) - Row 26-27 / F-009 / 1.3.4 (OT-SW) Querverweise: - Row 47 / F-029 / 5.2.1 (OT-Change-Mgmt) | O14: Policy Framework: - OT-Asset-Inventarisierungs-Verfahrensanweisung - Klassifikation OT-Assets (Level 0-3 nach Purdue-Modell) Standards: - IEC 62443-2-1 §SP.04 (Asset Inventory) - IEC 62443-3-2 (Risk Assessment & Zone/Conduit-Modell) - ISO/IEC 27001:2022 A.5.9 - VDA ISA 6.0.3 Kap. 1.3.1 / 1.3.4 Weitere Empfehlungen: - Tool-Auswahl: passives OT-Discovery (z. B. Claroty, Nozomi, Tenable.ot) für SK/PL - OT-Asset-Liste in Matrix42 als getrennte CMDB-Sicht - Kritikalitäts-Tagging je Anlage (Produktionsausfall-Folgekosten) | P14: Mark Lütz (SK/PL -> OT/PROD) | Q14: SK/PL | R14: Hoch | S14: Offen | T14: 46172 | W14: 1
A15: F-003 | B15: Information Security | C15: IS Policies and Organization | D15: 1.2.2 | E15: To what extent are information security responsibilities organized? | F15: Inwieweit sind Informationssicherheitsaufgaben organisiert? | G15: Major NC | H15: Information Sec. Anforderungen an OT Verträge und Assessment; Brandmeldeanlage, KLIMA etc. | I15: 2 | J15: 3 | K15: =IF(AND(ISNUMBER(I15),ISNUMBER(J15)),J15-I15,"") -> 1 | L15: Prüfung der bestehenden Verträge OT (SK/PL) -> wie sehen die verträge im OT bereich aus. Hot stand by mit Siemens zum beispiel. Gibt es updates für sps und wer stellt sie zu verfügung und testet und implementiert. Asset Liste hier erforderlich für vertragliche Gegebenheiten. | M15: Umsetzungsgegenstand: Prüfung und Anpassung bestehender OT-Wartungs-/Service-Verträge (SPS-Hersteller, Klima, BMA) gegen IS-Anforderungen (Hot-Standby, Patch-Bereitstellung, Testing, Datenfluss). Prozessbezug: VDA ISA 1.2.2 + 6.1.1; ISO 27001 A.5.19–A.5.22 (Lieferantenbeziehungen). Workflow Items: 1. Vertrags-Inventur OT-Lieferanten SK/PL (Owner: Plant Manager + Einkauf + ISB). 2. IS-Clause-Set: NDA, Incident-Notify, Patch-SLA, Asset-Listenpflege. 3. Nachverhandlung kritischer Verträge (z. B. Siemens Hot-Standby). Nachweis: Vertragsregister, IS-Annex je Vertrag, ISRA-Eintrag bei Restrisiko. Abhängigkeiten (Detail s. Spalte N): → Major NC; baut auf F-003 + F-001; treibt F-005/F-042/F-043 | N15: Vorgelagert: - Row 14 / F-003 / 1.2.2 (OT-Assetliste) - Row 7 / F-001 / 1.1.1 (Vertragsvorlagen) Nachgelagert: - Row 21 / F-005 / 1.2.4 (OLA) - Row 22 / F-005 / 1.2.4 (externe OT-Zugriffe) - Row 60 / F-042 / 6.1.1 (Supplier-IS-Mgmt) - Row 61 / F-043 / 6.1.2 (NDA) Querverweise: - Row 25 / F-008 / 1.3.3 (Externe IT-Dienste) | O15: Policy Framework: - RL OT-Lieferanten & Wartungspartner mit IS-Mindestanforderungen - Pflicht-Anhang IS-Klauseln (Logging, Zugriff, Incident-Meldung, Subunternehmer) - OT-Lieferanten-Assessment-Fragebogen (vor Vertragsabschluss) Standards: - ISO/IEC 27001:2022 A.5.19-A.5.23 - IEC 62443-2-4 (Security Programm-Anforderungen an Dienstleister) - VDA ISA 6.0.3 Kap. 6.1.x Weitere Empfehlungen: - Major NC: Bestandsverträge OT-Wartung systematisch nachverhandeln - Vertrags-Tracking in Einkaufstool integrieren (Eskalation bei IS-Lücke) - Auditrecht beim Lieferanten als Pflichtklausel | P15: Mark Lütz (SK/PL -> OT/PROD) | Q15: SK/PL | R15: Hoch | S15: Offen | T15: 46172 | W15: 1
A16: F-003 | B16: Information Security | C16: IS Policies and Organization | D16: 1.2.2 | E16: To what extent are information security responsibilities organized? | F16: Inwieweit sind Informationssicherheitsaufgaben organisiert? | G16: Observation | H16: ISO Nicht im Organigramm enthalten | I16: 2 | J16: 3 | K16: =IF(AND(ISNUMBER(I16),ISNUMBER(J16)),J16-I16,"") -> 1 | L16: Gibt es ein Organigramm auf Gruppenebene und wer ist für dieses dokument verantwortlich? wo steht das? | M16: Umsetzungsgegenstand: Aufnahme der ISB-Funktion in das Gruppen-Organigramm mit klar zugewiesener Berichtslinie an die Geschäftsleitung. Prozessbezug: VDA ISA 1.2.1/1.2.2; ISO 27001 Clause 5.3 (Rollen und Verantwortlichkeiten). Workflow Items: 1. Anpassung Gruppen-Organigramm (Owner: HR + GL). 2. ISB-Rolle als gestrichelte Linie zu allen Standorten visualisieren. 3. Freigabe und Ablage im BOS. Nachweis: aktuelles Organigramm, BOS-Verlinkung. Abhängigkeiten (Detail s. Spalte N): → Voraussetzung für F-002, F-003 und ISB-Eskalation aller Findings | N16: Vorgelagert: - keine (Stellenbeschreibung/Org-Strukturthema) Nachgelagert: - Row 11 / F-002 / 1.2.1 (Audit-Berichtsweg via ISB) - Row 13 / F-003 / 1.2.2 (OT-Verantwortlichkeiten) - ALLE Findings (ISB-Eskalationspfad) Querverweise: - Row 30 / F-012 / 1.5.2 (Unabhängigkeit der Review) | O16: Policy Framework: - Aktualisiertes Organigramm Reutter Group inkl. ISB-Position - ISB-Stellenbeschreibung mit direktem Berichtsweg Geschäftsleitung - Schnittstellen-Charta IT / CIO / Geschäftsleitung Standards: - ISO/IEC 27001:2022 A.5.2, A.5.3, A.5.4 - VDA ISA 6.0.3 Kap. 1.2.2 Regulatorisch: - NIS-2 Art. 20 (Verantwortung Leitungsorgane) Weitere Empfehlungen: - ISB-Reporting-Linie unabhängig von CIO (zur Geschäftsleitung) - ISB-Vertretungsregelung schriftlich fixieren - Organigramm im Mitarbeiterportal sichtbar machen | P16: Mark Lütz (SK/PL -> OT/PROD) | Q16: SK/PL | R16: Hoch | S16: Offen | T16: 46157 | W16: 1
A17: F-003 | B17: Information Security | C17: IS Policies and Organization | D17: 1.2.2 | E17: To what extent are information security responsibilities organized? | F17: Inwieweit sind Informationssicherheitsaufgaben organisiert? | G17: Major NC | H17: Fehlende Betrachtung der Informationssicherheit in Projekten (Sales, Engineering (PLM) und Purchaising (Supply Chaing) -> Beispiel: Wir haben ein Projekt, Kunde schickt ein NDA. Wer kennt den Inhalt und wie kommt dieser zu den Projektmitarbeitern ←genauso! Erzeugung Projekt Policy (!) | I17: 2 | J17: 3 | K17: =IF(AND(ISNUMBER(I17),ISNUMBER(J17)),J17-I17,"") -> 1 | L17: Infromationssicherheit in Projekten ist eines der heißesten Themen → Da sind wir (schlecht) Punkt 1.2.3. Erwartung das die Projekte als Vertaulich eingestuft werden, was bedeutet das bei den Kunden Projekte? Wie lange müssen und wie lange dürfen wir Projektdaten aufbewahren? Wie händeln wir das und wo ist es definiert- Beispiel 3-6 Monaten nach Projekt muss garantiert sein das die Projektdaten nicht mehr zugänglich sind. Übergabeworkflow von Sales zum Projekt > Hier existiert schon etwas - Abfragen gem. Screenshot. Wir haben ein Projekt, Kunde schickt ein NDA. Wer kennt den Inhalt und wie kommt dieser zu den Projektmitarbeitern ←genauso! Übergabe der Kundeninformationen Kundenabmachungen wie z.b. NDA muss in einen übergabe WF. Selbes für Vertragsinformationen (Beispiel: dürfen später sublieferenten verwendet werden, wie bekommt das prokjekt so ein Vertragsinfomrationsteil mit) -> Siehe Ausschnitt aus Screenshot was die Auditoren erwarten bzw. was in der Regel im Kontext mit der AL3 Zert. zu Gesicht bekommen. -> Screenshot StageReview 20.4.26 Expectations | M17: Umsetzungsgegenstand: Etablierung einer Projekt-Informationssicherheits-Richtlinie inkl. Klassifizierung, NDA-Handling, Sales→Projekt-Übergabe-Workflow sowie Aufbewahrungs- und Löschfristen für Projektdaten (3–6 Monate nach Projektabschluss). Prozessbezug: VDA ISA 1.2.3 (IS in Projekten); ISO 27001 A.5.8; OEM-Vertragsanforderungen. Workflow Items: 1. RL Projekt-Informationssicherheit (Owner: ISB + PMO). 2. STD Sales→Projekt-Handover-WF mit Pflichtfeldern Klassifizierung, NDA-Status, Sublieferanten-Restriktionen. 3. STD Projekt-Closure mit Datenlöschungs-/Archivierungs-WF. 4. Trainings für Sales, Engineering, Purchaising. Nachweis: RL freigegeben, Handover-Templates, Closure-Protokolle, Trainingsnachweise. Abhängigkeiten (Detail s. Spalte N): → Major NC; baut auf F-001/F-010/F-043; treibt F-004 + F-038 | N17: Vorgelagert: - Row 7 / F-001 / 1.1.1 (Doku-Lenkung) - Row 28 / F-010 / 1.4.1 (Risiko-Mgmt) - Row 61 / F-043 / 6.1.2 (NDA-Lifecycle) Nachgelagert: - Row 18 / F-004 / 1.2.3 (Konsolidierung Projekt-IS-RL) - Row 56 / F-038 / 5.3.1 (IS in neuen Systemen) Querverweise: - Row 9 / F-001 / 1.1.1 (Klassifizierung Prototypendaten) - Row 60 / F-042 / 6.1.1 (Supplier) | O17: Policy Framework: - RL Informationssicherheit in Projekten (gilt für ALLE Projekttypen) - Projekt-Initiierungs-Checkliste mit IS-Risk-Assessment - NDA-Templates (intern/extern/OEM) revisionssicher Standards: - ISO/IEC 27001:2022 A.5.8 (IS im Projektmanagement) - ISO/IEC 27005 (Risiko-Mgmt-Methodik) - VDA Prototypenschutz-Leitfaden (Pflicht bei OEM-Entwicklungsprojekten) - VDA ISA 6.0.3 Kap. 1.2.2 / 1.2.3 Weitere Empfehlungen: - Major NC: NDA-Vorlage durch externe Kanzlei prüfen lassen (Rechtsverbindlichkeit DE/AT/SK/PL) - IS-Gate im Projekt-Phasenmodell (Stage-Gate-Reviews) - Schulung Projektleiter zur IS-Risk-Assessment-Pflicht (TTT-Phase 3) | P17: ISB, GL, Hubertus Linz, Günther P., Hannes P. P. Göttling | Q17: Alle | R17: Hoch | S17: Offen | T17: 46172 | W17: 1
A18: F-004 | B18: Information Security | C18: IS Policies and Organization | D18: 1.2.3 | E18: To what extent are information security requirements considered in projects? | F18: Inwieweit werden Anforderungen an Informationssicherheit in Projekten berücksichtigt? | I18: 2 | J18: 3 | K18: =IF(AND(ISNUMBER(I18),ISNUMBER(J18)),J18-I18,"") -> 1 | M18: Umsetzungsgegenstand: Konsolidierung der Maßnahmen aus F-003/1.2.2 zu einer durchgängigen Projekt-IS-Vorgabe als zentraler AL3-Schwerpunkt gem. Stage-Review-Erwartung (20.04.26). Prozessbezug: VDA ISA 1.2.3; ISO 27001 A.5.8; OEM-Prototype-Protection. Workflow Items: 1. Übernahme F-003/Row 17 in dieses Finding. 2. Erweiterung um Engineering (PLM) und Procurement (Supply Chain). 3. Anbindung an ISRA für Projekt-Risikoeintrag. Nachweis: identisch zu F-003/Row 17 + Projekt-Risikoeintrag im ISRA. Abhängigkeiten (Detail s. Spalte N): → Konsolidierung; baut auf F-003 (Major NC) | N18: Vorgelagert: - Row 17 / F-003 / 1.2.2 (IS in Projekten — Major NC) - Row 7 / F-001 / 1.1.1 (Doku-Lenkung) Nachgelagert: - Row 21 / F-005 / 1.2.4 (SLA/OLA) - Row 56 / F-038 / 5.3.1 (IS in neuen Systemen) Querverweise: - Row 28 / F-010 / 1.4.1 (Risiko-Mgmt) | O18: Policy Framework: - Konsolidierte RL 'IS im Projekt- & Produktlebenszyklus' - Übergreifende Projekt-IS-Checkliste (Phase Initiation/Plan/Execute/Close) Standards: - ISO/IEC 27001:2022 A.5.8 - VDA ISA 6.0.3 Kap. 1.2.3 - PMI/IPMA-Projektmgmt-Standards mit IS-Add-on Weitere Empfehlungen: - Konsolidierung redundanter Projekt-Doku in einem Master-Dokument - Projektlistung mit IS-Risikoeinstufung als ISMS-Eingangsdokument | P18: ISB | Q18: Alle | R18: Hoch | S18: Offen | T18: 46142 | W18: 1
A19: F-General | B19: Information Security | C19: IS Policies and Organization | D19: 1.2.4 | E19: To what extent are the responsibilities between external IT service providers and the own organization defined? | F19: Inwieweit sind die Verantwortlichkeiten zwischen externen IT-Dienstleistern und der eigenen Organisation definiert? | G19: Observation | H19: Should = Must Requirements bis auf Diskurs für Nachweis, dass nicht applicable. | I19: 1 | J19: 3 | K19: =IF(AND(ISNUMBER(I19),ISNUMBER(J19)),J19-I19,"") -> 2 | L19: Wir müssen neben den High und Very High Availability Anforderungen immer die Must & Should Anforderungen mit Berücksichtigen. Es gibt die Möglichkeit Should Anforderungen wenn nicht applicable, wegzudiskutieren, dass ist aber kaum möglich! | M19: Umsetzungsgegenstand: Strikte Behandlung aller 'Should'-Anforderungen als faktisch verpflichtend; Ausnahmen nur mit dokumentierter Risikoabwägung und ISB-Approval. Prozessbezug: VDA ISA 1.2.4 (Service-Provider) – übergreifende Methodik; ISO 27001 Clause 6.1.3 (SoA). Workflow Items: 1. SoA-Eintrag pro 'Should'-Ausnahme inkl. Risikoreferenz. 2. ISB-Freigabe vor Auditeintragung. Nachweis: SoA, ISRA-Eintrag, Approval-Workflow im BOS. Abhängigkeiten (Detail s. Spalte N): → methodisch; betrifft Auslegung ALLER Should-Controls | N19: Vorgelagert: - keine (methodischer Hinweis) Nachgelagert: - ALLE 'Should'-Findings (Nachweispflicht statt Optionalität) Querverweise: - Row 4 / F-General (AL3-Niveau) - Row 20 / F-General (Doku-Priorität) | O19: Policy Framework: - ISMS-Maturity-Strategie: 'Should = Must' für AL3 dokumentieren Standards: - VDA ISA 6.0.3 (Maturity-Argumentation) - ENX AL3-Leitfaden Weitere Empfehlungen: - Auditor-Frühabstimmung zur 'Should'-Auslegung - Im SoA: für 'Should'-Controls Nachweis-Strategie hinterlegen | P19: All | Q19: Alle | R19: Hoch | S19: Offen | T19: 46142 | W19: 1
A20: F-General | B20: Information Security | C20: IS Policies and Organization | D20: 1.2.4 | E20: To what extent are the responsibilities between external IT service providers and the own organization defined? | F20: Inwieweit sind die Verantwortlichkeiten zwischen externen IT-Dienstleistern und der eigenen Organisation definiert? | G20: Observation | H20: ENX -> Dokumentierte Umsetzung wichtiger als Policies (!) / e.g.: Wiederherstellung zeigen ! | I20: 1 | J20: 3 | K20: =IF(AND(ISNUMBER(I20),ISNUMBER(J20)),J20-I20,"") -> 2 | L20: Die Etablierung der Verfahren und der Nachweis der Umsetzungen ist wichtiger als die Evidenz der Verfügbarkeit des Policy Frameworks ! | M20: Umsetzungsgegenstand: Verschiebung des Nachweisschwerpunkts von der reinen Policy-Verfügbarkeit hin zu Verfahren und Wirksamkeitsnachweisen (Recovery-Demo, Onboarding-Walkthrough, Incident-Drill). Prozessbezug: VDA ISA AL3-Reifegradlogik; ENX-Audit-Erwartung; ISO 27001 Clause 9.1. Workflow Items: 1. Mapping Policy → Verfahren → Nachweis je Kontrolle (Owner: ISB). 2. Aufbau Evidence-Repository (TISAX-Auditfile) je Kontrolle. 3. Demo-Termine für ausgewählte Verfahren (Recovery, Incident, Onboarding). Nachweis: Evidence-Repository, Demo-Protokolle. Abhängigkeiten (Detail s. Spalte N): → methodisch; betrifft Audit-Nachweisstrategie aller Findings | N20: Vorgelagert: - keine (methodischer Hinweis ENX) Nachgelagert: - ALLE Findings (Umsetzungsnachweis vor Policy-Doku) Querverweise: - Row 19 / F-General (Should=Must) | O20: Policy Framework: - Verschiebung des Doku-Schwerpunkts: Verfahrensanweisungen + Nachweise > reine Policies Standards: - ENX VDA ISA 6.0.3 Auditmethodik - ISO/IEC 27001:2022 §7.5 (Dokumentierte Information als Nachweis) Weitere Empfehlungen: - Auditfile-Struktur: pro Control 1 Policy + N Nachweise (Screenshots, Tickets, Protokolle) - ISB-Audit-File 'Wirksamkeit' als zentraler Folder | P20: All | Q20: Alle | R20: Hoch | S20: Offen | T20: 46142 | W20: 1
A21: F-005 | B21: Information Security | C21: IS Policies and Organization | D21: 1.2.4 | E21: To what extent are the responsibilities between external IT service providers and the own organization defined? | F21: Inwieweit sind die Verantwortlichkeiten zwischen externen IT-Dienstleistern und der eigenen Organisation definiert? | G21: Major NC | H21: Welche internen OLAs existieren und sind vereinbart, welche OT SLAs sind in Verträgen vereinbart und mit dem Mgmt. abgestimmt? Training und lfd. Prozess für OLA und SLA Mgmt. inkl. KPI Darstellung. | I21: 1 | J21: 3 | K21: =IF(AND(ISNUMBER(I21),ISNUMBER(J21)),J21-I21,"") -> 2 | L21: IT & OT Service Provider; Verträge für SK/PL betrachten und erörtern; (SPS Ausfall und vertragliche Vereinbarung), MTO/RTP/RTO Anforderungen an OT, ext. Zugriff und Authentifizierung. Personalisierte Accounts vom ext. Serv. Provider. SLA und OLA für OT- Wo sind die, wer prüft das, welche SLA Agreements sind mit den Externen getroffen. Gleiches gilt für PLM oder AX in Polen. MAximal tolerierte Ausfallzeiten, sind diese definiert und matcht das mit den Verträgen Sinn und wenn nicht ist das Risiko bewertet | M21: Umsetzungsgegenstand: Erfassung und Bewertung aller internen OLAs und externen SLAs für IT- und OT-Dienste (SPS-Wartung, PLM, AX-Polen) inkl. RTO/RPO und personalisierter Accounts externer Dienstleister. Prozessbezug: VDA ISA 1.2.4 + 5.2.8 (Kontinuität); ISO 27001 A.5.19–A.5.23. Workflow Items: 1. SLA/OLA-Register (Owner: IT-Leitung + Plant Manager + ISB). 2. Bewertung Maximum-Tolerable-Outage vs. Vertragslage; ISRA-Eintrag bei Lücken. 3. Personalisierte Service-Provider-Accounts (kein Shared-Access). 4. KPI-Reporting SLA-Einhaltung. Nachweis: SLA/OLA-Register, ISRA, KPI-Report. Abhängigkeiten (Detail s. Spalte N): → Major NC; baut auf F-003/F-006/F-004 | N21: Vorgelagert: - Row 13 / F-003 / 1.2.2 (OT-Verantwortlichkeiten) - Row 23 / F-006 / 1.3.1 (Asset Mgmt) - Row 18 / F-004 / 1.2.3 (IS in Projekten) Nachgelagert: - Row 22 / F-005 / 1.2.4 (externe OT-Zugriffe) - Row 57 / F-039 / 5.3.2 (Netzwerk-SLA) - Row 60 / F-042 / 6.1.1 (Supplier-Mgmt) Querverweise: - Row 15 / F-003 / 1.2.2 (OT-Verträge) | O21: Policy Framework: - OLA-Master für IT-interne Dienste - OLA IT ↔ OT mit Service-Verfügbarkeiten je Anlage/Werk - SLA-Vorlage für externe Wartungspartner Standards: - ISO/IEC 27001:2022 A.5.19-A.5.23 - ITIL 4 Service Level Management - IEC 62443-2-4 (Anforderungen an Service-Provider) - VDA ISA 6.0.3 Kap. 1.2.4 Weitere Empfehlungen: - Major NC: OLA IT/OT für alle 4 Standorte schriftlich (Pflicht für AL3) - Eskalationsmatrix bei OLA-Verletzung (CIO/CFO) - Quartals-Review OLA-Erfüllung als ISMS-KPI | P21: All | Q21: Alle | R21: Hoch | S21: Offen | T21: 46142 | W21: 1
A22: F-005 | B22: Information Security | C22: IS Policies and Organization | D22: 1.2.4 | E22: To what extent are the responsibilities between external IT service providers and the own organization defined? | F22: Inwieweit sind die Verantwortlichkeiten zwischen externen IT-Dienstleistern und der eigenen Organisation definiert? | G22: Minor NC | H22: Fehlener Prozess für Dokumentation von externen Zugriffsszenarien (wer, wie, wielange, worauf, encr. Meth.) im OT Bereich. | I22: 1 | J22: 3 | K22: =IF(AND(ISNUMBER(I22),ISNUMBER(J22)),J22-I22,"") -> 2 | L22: Wie wird das mit externen Service Providern u. Vertragshaltern umgesetzt, wer greift zu, was darf er, wie lange darf er und wie sieht der Request und die Umsetzung aus. Wie wird der Zugriff dokumentiert, so dass es auch eine Historie gibt. Personalisierte Accounts vom ext. Serv. Provider sind nur erlaubt. | M22: Umsetzungsgegenstand: Prozess für Dokumentation externer OT-Zugriffe (Wer / Worauf / Wie lange / Welche Verschlüsselung) mit historischer Nachvollziehbarkeit. Prozessbezug: VDA ISA 1.2.4 + 4.2.1 (Zugriffsrechte); ISO 27001 A.8.2/A.8.5; IEC 62443-3-3 SR 1.1. Workflow Items: 1. STD 'Remote Access OT' (Owner: ISB + OT-Lead). 2. Jump-Host/Bastion-Konzept mit Session-Recording. 3. Approval-Workflow pro Zugriff (max. Gültigkeitsdauer). 4. Audit-Trail-Reporting. Nachweis: STD, Logs-Stichprobe, Approval-Tickets. Abhängigkeiten (Detail s. Spalte N): → baut auf F-005/F-003; treibt F-025/F-026/F-042 | N22: Vorgelagert: - Row 21 / F-005 / 1.2.4 (OLA) - Row 15 / F-003 / 1.2.2 (OT-Verträge) Nachgelagert: - Row 43 / F-025 / 4.1.3 (Account-Mgmt EXT) - Row 44 / F-026 / 4.2.1 (PAM/JIT für externe) - Row 60 / F-042 / 6.1.1 (Supplier) Querverweise: - Row 50 / F-032 / 5.2.4 (Logging externer Zugriffe) | O22: Policy Framework: - Verfahrensanweisung 'Externe Zugriffe' (IT/OT) inkl. Approval-Workflow - Vendor-Access-Request-Formular - Zeitlich befristete Zugänge (JIT) als Default Standards: - ISO/IEC 27001:2022 A.8.2, A.8.3, A.8.18 - IEC 62443-3-3 SR 2.1 / SR 2.2 (Access Control für OT) - VDA ISA 6.0.3 Kap. 1.2.4 / 4.x Weitere Empfehlungen: - PAM-Tool für externe OT-Wartung (z. B. CyberArk, BeyondTrust) - Session-Recording als Pflicht-Logging - Quartals-Audit externe Konten (Stale-Account-Detektion) | P22: All | Q22: Alle | R22: Hoch | S22: Offen | T22: 46142 | W22: 1
A23: F-006 | B23: Information Security | C23: IS Policies and Organization | D23: 1.3.1 | E23: To what extent are information assets identified and recorded? | F23: Inwieweit werden Informationsressourcen erfasst und dokumentiert? | G23: Minor NC | H23: Überprüfung: Sind die Netzwerkdevices im Matrix42 erfasst? Erfassung der OT Devices neben Matrix42 in den gen. Listen für SK und PL (Erweiterung um IP Comm.) | J23: 4 | K23: =IF(AND(ISNUMBER(I23),ISNUMBER(J23)),J23-I23,"") | L23: Beim Asset Mgmt.: Storages und Server bzw. windows devices sollten klar sein. OT Assests kommen in die Liste aber wie sieht es mit Software oder Dokumenten oder Backups oder Finanzdaten als Assests aus, auch diese müssen geführt werden. Rücksprache mit GL bzgl. besondere Finance-Assets als auch andere Assets. Welche weiteren Assetzuordnungen existieren noch? Welche Assets verlässt das unternehmen. Beispiel: Backups die in der cloud sind. Vorschlag: Anpassung Policy für Prozess und Klassifizierung (jährlich) für "besondere" Assets. Prüferfrage "beliebt": End2end Check in Matrix42 für Asset | M23: Umsetzungsgegenstand: Erweiterung des Asset Managements über klassische IT-Assets hinaus auf OT-Devices, Software, Dokumente, Backups, Finanzdaten und Cloud-resident Assets; jährlicher Klassifizierungs-Review. Prozessbezug: VDA ISA 1.3.1; ISO 27001 A.5.9. Workflow Items: 1. Asset-Klassifizierungsschema (Owner: ISB): IT-HW, OT-HW, SW, Daten, Dokumente, Finanzdaten, Cloud-Assets. 2. Anpassung Asset-Mgmt-Policy: jährlicher Review, 'besondere' Assets (Finance, Backups). 3. End-to-End-Test in Matrix42 (Auditor-Standardfrage). Nachweis: Asset-Register vollständig, Klassifizierungsbericht, Matrix42-Audit-Trail. Abhängigkeiten (Detail s. Spalte N): → Fundament: Voraussetzung für F-003, F-007, F-010, F-027, F-033 | N23: Vorgelagert: - keine (Fundamentbaustein) Nachgelagert: - Row 14 / F-003 / 1.2.2 (OT-Assetliste) - Row 24 / F-007 / 1.3.2 (Private Geräte) - Row 28 / F-010 / 1.4.1 (Risiko-Mgmt: Assets als Schutzobjekt) - Row 45 / F-027 / 5.1.1 (Crypto: Assets benötigen Klassifikation) - Row 51 / F-033 / 5.2.5 (Vulnerability Mgmt) - Row 53 / F-035 / 5.2.7 (Netzwerk-Doku) - Row 55 / F-037 / 5.2.9 (Backup-Scope) Querverweise: - Row 49 / F-031 / 5.2.3 (Malware-Schutz-Scope) | O23: Policy Framework: - RL Asset Management (IT + OT + Information) - CMDB-Pflege-Verfahren (Matrix42) inkl. OT-Discovery-Integration Standards: - ISO/IEC 27001:2022 A.5.9-A.5.10 - ISO/IEC 19770 (IT Asset Management) - IEC 62443-2-1 §SP.04 - VDA ISA 6.0.3 Kap. 1.3.1 Weitere Empfehlungen: - Vollständigkeitsprüfung: Netzwerkdevices, IoT, OT-Anlagen, mobile Geräte - Asset-Ownership pro Standort eindeutig zuweisen - Asset-Liste als Eingangsgröße für Risk Register | P23: All | Q23: Alle | R23: Hoch | S23: Offen | T23: 46142 | W23: 1
A24: F-007 | B24: Information Security | C24: IS Policies and Organization | D24: 1.3.2 | E24: To what extent are information assets classified and managed in terms of their protection needs? | F24: Inwieweit werden Informationsressourcen entsprechend ihren Schutzanforderungen klassifiziert und verwaltet? | G24: Major NC | H24: Zugriff von nicht-unternehmens Endgeräten auf Unternehmensdaten aktuell gegeben. Diskurs: Abschalten oderRisikobewertung. Policy Vorgaben Siehe auch die novierte Legacy Policy (PG) mit der Anleitung. Word to PDF, Google Translate, Deepl.com etc. | I24: 2 | J24: 3 | K24: =IF(AND(ISNUMBER(I24),ISNUMBER(J24)),J24-I24,"") -> 1 | L24: Kein Zugriff von privaten Geräten auf Unternehmensinfrastruktur Asset Mgmt. Policy oder Bezug auf Unternehmensgeräte anpassen: 6.5 Speicherung, Transport, Remote Access und Cloud (eMail, Teams, OneDrive - Austausch von Daten). HomeOffice -> Printer usage (TBD); Risikobewertung -> Monitoring/Logging mit Maßnahmenplan organisatorische Maßnahme (Verbot und Verfahrensanweisung)/ eMail-Versandt (!) Konkretisierung von nicht Unternehmensgeräten Vertrauliche Daten dürfen nur auf Firmengeräte das ist bei uns nicht gegeben. Webzugang zu MS Zuhause drucken abschalten- Risiko bewerten in Bezug auf die vertraulichkeit die geschützt werden muss Webmail abschalten wie stellst du sicher das keine online umwandlung oder translation von informationen stattfindet ( als beispiel für daten die das unterehmen verlassen) | M24: Umsetzungsgegenstand: Unterbindung des Zugriffs nicht registrierter (privater) Endgeräte auf Unternehmensdaten; technische Durchsetzung über Conditional Access, DLP-Regeln gegen Cloud-Konverter/-Translate und Web-Mail-Sperre extern. Prozessbezug: VDA ISA 1.3.2 + 3.1.4 + 4.1.2; ISO 27001 A.6.7, A.8.1, A.8.20. Workflow Items: 1. Asset-Mgmt-Policy Kap. 6.5 ergänzen (Storage, Transport, Remote Access, Cloud). 2. Conditional Access 'Compliant Device' aktivieren. 3. DLP-Regeln gegen Upload zu Online-Translate/-Convert. 4. Drucken im Home-Office deaktivieren bzw. risikobewerten. 5. Verbots-Verfahrensanweisung + Monitoring. Nachweis: RL, CA-Policy-Export, DLP-Reports, Verfahrensanweisung freigegeben. Abhängigkeiten (Detail s. Spalte N): → Major NC; baut auf F-006/F-022; treibt F-019/F-024 | N24: Vorgelagert: - Row 23 / F-006 / 1.3.1 (Asset Mgmt) - Row 40 / F-022 / 3.1.4 (Mobile Geräte) Nachgelagert: - Row 37 / F-019 / 2.1.4 (Remote Work) - Row 42 / F-024 / 4.1.2 (MFA) Querverweise: - Row 9 / F-001 / 1.1.1 (Klassifizierung 'Intern') | O24: Policy Framework: - RL BYOD / Private Endgeräte (Verbot oder MDM-Container) - Acceptable-Use-Policy mit klarer Trennung Privat/Unternehmen - Betriebsvereinbarung mit Betriebsrat (mehrsprachig) Standards: - ISO/IEC 27001:2022 A.8.1 - ISO/IEC 27031, ISO/IEC 27033 (Netzwerksicherheit) - VDA ISA 6.0.3 Kap. 1.3.2 Regulatorisch: - DSGVO Art. 32 (technisch-organisatorische Maßnahmen) Weitere Empfehlungen: - Major NC: technische Durchsetzung via Conditional Access (M365) + MDM - Awareness: Phishing-Kampagnen + TTT-Phase 2 zu BYOD-Risiken - Stichprobe-Audit private Geräte-Zugriffe in Logs | P24: All | Q24: Alle | R24: Hoch | S24: Offen | T24: 46142 | W24: 1
A25: F-008 | B25: Information Security | C25: IS Policies and Organization | D25: 1.3.3 | E25: To what extent is it ensured that only evaluated and approved external IT services are used for processing the organization’s information assets? | F25: Inwieweit wird sichergestellt, dass nur evaluierte und genehmigte externe IT-Dienste zur Verarbeitung der Informationsressourcen der Organisation verwendet werden? | G25: Observation | H25: Fehlende Integration eines Assessment für Inf.Sich. Risikobewertung inkl. CIA von externen IT-Providern und dem Zugang/Zutritt auf interne IT-Infr.; gleiches für SW. Vorgaben existieren für verschiedenste Szenarien -> zusammenfassen und in die Vorgaben integrieren. | I25: 2 | J25: 3 | K25: =IF(AND(ISNUMBER(I25),ISNUMBER(J25)),J25-I25,"") -> 1 | L25: Wenn PC nicht geht dann ticket. -> Wenn Machinine nicht geht dann? Wenn intern das problem nicht behoben werden kann, wer entscheidet und ist verantwortlich für externe unterstützung und gibt es eine liste an externen freigegebenen Partnern und der damit einhergehenden Kritierien. Das gleiche gilt für Freigebene Softwarelösungen- Wer darf wen bei was kontaktieren und wo steht es? | M25: Umsetzungsgegenstand: Integration eines verbindlichen IS-/CIA-Risikoassessments für externe IT-Provider, IT-Dienste und Software vor Beauftragung; Konsolidierung bestehender Vorgaben in einem einheitlichen Standard. Prozessbezug: VDA ISA 1.3.3; ISO 27001 A.5.19, A.5.21, A.5.23. Workflow Items: 1. STD 'External IT Service Assessment' (Owner: ISB). 2. Liste freigegebener Partner inkl. Auswahl-Kriterien. 3. Approval-Workflow für Notfall-Beauftragung (Maschinenausfall) mit Eskalationspfad. 4. Aufnahme bestehendes SaaS-Assessment-Toolset (M. Lütz). Nachweis: STD, Freigabeliste, Assessment-Berichte, ISRA-Verknüpfung. Abhängigkeiten (Detail s. Spalte N): → baut auf F-006; treibt F-040/F-041/F-039 | N25: Vorgelagert: - Row 23 / F-006 / 1.3.1 (Asset Mgmt — externe Services als Asset) Nachgelagert: - Row 58 / F-040 / 5.3.3 (Cloud-Disposal) - Row 59 / F-041 / 5.3.4 (Mandantentrennung) - Row 57 / F-039 / 5.3.2 (Netzwerk-SLA) Querverweise: - Row 15 / F-003 / 1.2.2 (OT-Lieferanten) - Row 60 / F-042 / 6.1.1 (Supplier-Mgmt) | O25: Policy Framework: - RL Cloud & Outsourcing-Sicherheit - Cloud-Assessment-Tool (Reutter-intern, M. Lütz) als Pflicht-Eingangs-Tor - Vendor-Risk-Scorecard Standards: - ISO/IEC 27017 (Cloud-Sicherheit) - ISO/IEC 27018 (PII in Cloud) - BSI C5:2020 (Cloud Computing Compliance) - VDA ISA 6.0.3 Kap. 1.3.3 / 5.3.x Weitere Empfehlungen: - Bestehende SaaS-Tools (M365, Sophos, Matrix42) erneut assessen - 'Schatten-IT'-Discovery (CASB / M365 Cloud App Discovery) - Datenklassifikations-Mapping je Cloud-Tool | P25: All | Q25: Alle | R25: Hoch | S25: Offen | T25: 46142 | W25: 1
A26: F-009 | B26: Information Security | C26: IS Policies and Organization | D26: 1.3.4 | E26: To what extent is it ensured that only evaluated and approved software is used for processing the organization’s information assets? | F26: Inwieweit wird sichergestellt, dass nur geprüfte und genehmigte Software zur Verarbeitung der Informationsressourcen der Organisation verwendet wird? | G26: Minor NC | H26: Fehlender Review und Prozess für freigegeben SW. Keine Nachweise wie OT Maintenance im Wartungszyklus bewertet für neue SW und oder zusätzlicher SW. | I26: 2 | J26: 3 | K26: =IF(AND(ISNUMBER(I26),ISNUMBER(J26)),J26-I26,"") -> 1 | L26: Zyklischer Review der bereits freigegeben SW im Bezug auf IT- oder SW-Ownership und Rückfragen, ob in dieser Form noch genutzt oder nicht, wer ist hier der Reviewer? Aufbau Liste für PDCA und Prozess für Tracking/Review und Entscheidung. OT nachprüfen für Prozesse bei OT-DL Querschnittsfunktionen, e.g. wie wird sichergestellt, dass während Maintenance (Wartungszyklus) keine zusätzliche SW installiert wird. | M26: Umsetzungsgegenstand: Zyklischer Review freigegebener Software inkl. SW-Owner, Nutzungsstatus, Aktualität; Verfahren zur Kontrolle der Wartungsfenster im OT-Bereich gegen unautorisierte SW-Installation. Prozessbezug: VDA ISA 1.3.4 + 5.2.1 + 5.2.3; ISO 27001 A.8.19, A.8.32. Workflow Items: 1. SW-Liste mit Owner und Review-Datum (Owner: IT-Leitung). 2. PDCA-Review-Zyklus halbjährlich. 3. OT-Wartungsprotokoll mit Vor-/Nach-Wartungs-Konfigurations-abgleich. Nachweis: SW-Liste mit Review-Status, OT-Wartungsprotokolle, Stichproben. Abhängigkeiten (Detail s. Spalte N): → baut auf F-006; treibt F-029/F-033 | N26: Vorgelagert: - Row 23 / F-006 / 1.3.1 (Asset Mgmt — SW als Asset) Nachgelagert: - Row 47 / F-029 / 5.2.1 (Change Mgmt) - Row 51 / F-033 / 5.2.5 (Vulnerability Mgmt) Querverweise: - Row 27 / F-General / 1.3.4 (IEC 62443-Konformität) - Row 49 / F-031 / 5.2.3 (Malware-Schutz) | O26: Policy Framework: - RL Software-Freigabe & Whitelisting - SBOM-Pflicht (Software Bill of Materials) für OT-/Steuerungssoftware Standards: - ISO/IEC 27001:2022 A.8.19, A.8.30 - IEC 62443-4-1 (Secure Product Development Lifecycle) - NIST SSDF (SP 800-218) - VDA ISA 6.0.3 Kap. 1.3.4 Regulatorisch: - EU Cyber Resilience Act (CRA) — Vorbereitung Weitere Empfehlungen: - SW-Freigabe-Workflow in Matrix42 abbilden - AppLocker / WDAC-Pilot in Office-Umgebung - OT-SW-Whitelist je Anlage SK/PL/AT | P26: All | Q26: IT / SK / PL | R26: Hoch | S26: Offen | T26: 46142 | W26: 1
A27: F-General | B27: Information Security | C27: IS Policies and Organization | D27: 1.3.4 | E27: To what extent is it ensured that only evaluated and approved software is used for processing the organization’s information assets? | F27: Inwieweit wird sichergestellt, dass nur geprüfte und genehmigte Software zur Verarbeitung der Informationsressourcen der Organisation verwendet wird? | G27: Observation | H27: Immer darauf achten wenn die ISA/IEC 62443 referenziert wird (in der Spalte P) muss OT mehr Berücksichtigt werden( Security for industrial automation and control systems) | I27: 2 | J27: 3 | K27: 1 | L27: Durchführung Assessment Prüfkatalog wo ISA/IEC 62443 gegeben in Spalte P für den OT Kontext und Prüfung der Konformität für OT. Erstelllung Liste mit entspr. Vorgaben für Maßnahmen und Umsetzungen | M27: Umsetzungsgegenstand: Systematische OT-Konformitätsprüfung aller VDA-ISA-Kontrollen mit IEC-62443-Referenz (Spalte P) und Ableitung OT-spezifischer Umsetzungsmaßnahmen. Prozessbezug: VDA ISA Spalte P (IEC 62443); IEC 62443-2-1/-3-3. Workflow Items: 1. Filter ISA-Excel auf IEC-62443-markierte Kontrollen (Owner: ISB). 2. OT-Gap-Analyse pro Kontrolle. 3. Maßnahmenliste IT/OT-getrennt mit Verknüpfung zu OT-Patch-/VM-Standard. Nachweis: Gap-Analyse-Bericht, Maßnahmenliste, ISRA-Eintrag. Abhängigkeiten (Detail s. Spalte N): → baut auf F-003 (OT-Verantw./Assets); treibt alle OT-5.2.x-Findings | N27: Vorgelagert: - Row 13 / F-003 / 1.2.2 (OT-Verantwortlichkeiten) - Row 14 / F-003 / 1.2.2 (OT-Assetliste) Nachgelagert: - ALLE OT-Findings (5.2.5, 5.2.6, 5.2.7, 5.2.9) - Row 47 / F-029 / 5.2.1 (OT-Change-Mgmt) Querverweise: - Row 26 / F-009 / 1.3.4 (SW-Review) | O27: Policy Framework: - OT-Security-Rahmenrichtlinie (REUTIB) konform IEC 62443 - OT-Architektur-Standards mit Purdue-Modell-Referenz Standards: - IEC 62443-2-1, -3-2, -3-3, -4-1, -4-2 (vollständige Reihe) - ISO/IEC 27019 (Energieversorgung; übertragbar auf Fertigung) - VDA ISA 6.0.3 Kap. 1.3.4 Weitere Empfehlungen: - IEC 62443 als verbindlicher Konformitätsrahmen im SoA verankern - OT-Spezialaudit durch externen IEC-62443-Lead-Auditor (separat zu CIS) - Schulung OT-Lead je Werk in IEC 62443 | P27: ISB | Q27: Alle | R27: Hoch | S27: Offen | T27: 46142 | W27: 1
A28: F-010 | B28: Information Security | C28: IS Policies and Organization | D28: 1.4.1 | E28: To what extent are information security risks managed? | F28: Inwieweit werden Informationssicherheitsrisiken gesteuert? | G28: Minor NC | H28: Ist die OT Bestandteil der Inf/RM Teams für Verantwortlichkeiten (?) Fehlender Zweizeiler der Risikobetrachtung in der Risiko RL. Very High Availability Request: '+ Additional requirements for software use (e.g., need for control or monitoring of usage) are determined (if any) (C, I, A) | I28: 2 | J28: 3 | K28: =IF(AND(ISNUMBER(I28),ISNUMBER(J28)),J28-I28,"") -> 1 | L28: Befüllung und Risikobehandlung im ISW. Nachprüfung für IT/OT, wo analog Gremiensteckbrief (STD) enthalten, insbesondere OT. Controls gem. ISA Katalog für Betrachtung -> Zweizeiler für Risikotrachtung in der RL. Risikotabelle: Erweiterung mit Control-Nr. TISAX Katalog 6.03 ISRA nicht nur befüllen sondern auch die Ableitungen (Maßnahmen / Umsetzung) daraus definieren und tracken sowie regelmäßiges review planen und dokumentieren In der ISRA Richtlinie fehlt ggf. OT Kann man nachweisen das jedes controll aus dem Katalog also jeder Punkt im ISRA betrachtet wurde. Ein satz hintzufügen das alle controlls von tisax betrachtet werden sowie die kontrollnummer aus dem katalog hinzufügen. | M28: Umsetzungsgegenstand: Vervollständigung des Informationssicherheits-Risikomanagements um OT-Verantwortlichkeiten, Erweiterung ISRA um Control-Nr.-Referenzen VDA ISA 6.0.3 und expliziter Nachweis vollständiger Kontrollbetrachtung. Prozessbezug: VDA ISA 1.4.1; ISO/IEC 27005; BSI-Standard 200-3. Workflow Items: 1. ISRA-Tabelle erweitern (Owner: ISB): Spalten 'VDA-Kontroll-Nr.', 'Maßnahme abgeleitet', 'Review-Datum'. 2. ISRA-Richtlinie um OT-Scope und Gremiensteckbrief ISW ergänzen. 3. Statement: 'Alle VDA-ISA-Kontrollen werden im ISRA betrachtet.' 4. Maßnahmen-Tracking + Review-Plan. Nachweis: ISRA mit vollständigem Mapping, Review-Protokolle. Abhängigkeiten (Detail s. Spalte N): → baut auf F-006/F-003; Voraussetzung für F-011, F-015, F-029, F-033 | N28: Vorgelagert: - Row 23 / F-006 / 1.3.1 (Asset Mgmt als Schutzobjekt-Inventar) - Row 13 / F-003 / 1.2.2 (OT-Verantwortlichkeiten) Nachgelagert: - Row 17 / F-003 / 1.2.2 (IS in Projekten — Risk-Assessment) - Row 29 / F-011 / 1.5.1 (Wirksamkeit benötigt Risikobasis) - Row 33 / F-015 / 1.6.3 (BIA als BCM-Eingang) - Row 47 / F-029 / 5.2.1 (Change Risk Assessment) - Row 51 / F-033 / 5.2.5 (Vulnerability Risk Scoring) Querverweise: - Row 42 / F-024 / 4.1.2 (MFA-Risikoeinschätzung) - Row 44 / F-026 / 4.2.1 (RBAC-Risikoeinschätzung) | O28: Policy Framework: - RL Informationssicherheits-Risiko-Mgmt (ISRM) - Risiko-Bewertungsmethodik mit Skala 1–5 × 1–5 - ISRA-Vorlage mit Pflichtfeld 'VDA-Control-Nr.' Standards: - ISO/IEC 27001:2022 §6.1.2, §6.1.3, §8.2, §8.3 - ISO/IEC 27005:2022 (Risiko-Mgmt) - IEC 62443-3-2 (OT-Risiko-Mgmt mit Zonen/Conduits) - VDA ISA 6.0.3 Kap. 1.4.1 Weitere Empfehlungen: - OT-Mitwirkung im Risk-Team verbindlich (SK/PL Lead) - Risikoregister im ISMS-Tool zentral, mit Mapping zu Findings - Quartals-Risk-Review als Pflicht-Termin (CIO/CFO) - Risk-Treatment-Plan (RTP) als formales Dokument je Risiko ≥ Stufe 4 | P28: All | S28: Offen | W28: 1
A29: F-011 | B29: Information Security | C29: IS Policies and Organization | D29: 1.5.1 | E29: To what extent is compliance with information security ensured in procedures and processes? | F29: Inwieweit wird die Einhaltung der Informationssicherheit in Verfahren und Abläufen gewährleistet? | G29: Minor NC | H29: Gibt es für die Verfahren und Abläufe Controls für eine belastbare und nachweisliche Dokumentation (e.g. gibt es einen Plan für Kontrollgänge?). Auditprogramm mit einfließen lassen für Kontrollfokus. Fokus ist die Umsetzung; (e.g. schaut jemand das man tatsächlich nur ins Werk/Plant kommt wie vorgeschrieben, e.g. werden dieLlieferanten bewertet wie vorgeschrieben, technische Inf.Sec. Überprüfung erfolgt durch Matrix42 im HInblick auf ...) Existieren Überprüfungen auf die man referenzieren kann? Neben der Dokumentation der Wirksamkeitsnachweis (wirksame Umsetzung e.g. Lieferantenbewertung) sind Anpassungen an der Dokumentation wesentlich. Betrachtungszeitraum mindestens 1 Jahr (jährliche Überprüfung und Revision). Darstellung Zeitplan für Umsetzung ist notwendig. Was live nicht funktioniert, wurde das dann angepasst und auch in der Richtline angepasst. dafür muss es aber erstmal “live” sein. Muss mit einem Zeitplan dargestellt werden. Auch beim Patchmanagement z.B. | I29: 2 | J29: 3 | K29: =IF(AND(ISNUMBER(I29),ISNUMBER(J29)),J29-I29,"") -> 1 | L29: Einführung der Verifizierung durch Kontrollen und Bewertung der Umsetzung und Dokumentation als Wirksamkeitsnachweis. Auditprogramm und Control Compliance Framework kann hier helfen für den richtigen umsetzbaren Ansatz in der Verifizierung. Betrachtungszeitrum mind. 1 Jahr für jährliche Revision und Nachweise und Wirksamkeitsanalyse. Die Verantwortlichen müssen für die Prozesse die Nachweise liefern können. Im Umkehrschluss muss bei Auffälligkeiten auch eine Richtline und Standard angepasst werden könnne (TISAX Fokus gegeben). | M29: Umsetzungsgegenstand: Control-Compliance-Framework mit Verifizierungskontrollen, Wirksamkeitsnachweisen und 12-Monats-Betrachtungszeitraum als Kern-AL3-Anforderung. Prozessbezug: VDA ISA 1.5.1; ISO 27001 Clause 9.1. Workflow Items: 1. Kontrolltest-Plan je Verfahren (Owner: ISB) — z. B. Stichproben Lieferantenbewertung, Werkszugang-Test, Matrix42-Compliance-Report. 2. Integration in internes Auditprogramm. 3. Anpassungsregel: bei Befund Wirksamkeitslücke → Richtlinien-Update. 4. 12-Monats-Revisionszyklus. Nachweis: Kontrolltest-Plan, Stichprobenprotokolle, Anpassungshistorie Policies, Zeitplan-Tabelle. Abhängigkeiten (Detail s. Spalte N): → AL3-Kern; baut auf F-002/F-010/F-032; treibt ALLE Major NCs + F-012 | N29: Vorgelagert (zwingend): - Row 11 / F-002 / 1.2.1 (Auditprogramm) - Row 12 / F-002 / 1.2.1 (KPIs) - Row 28 / F-010 / 1.4.1 (Risiko-Mgmt) - Row 50 / F-032 / 5.2.4 (Logging als Datenquelle) Nachgelagert: - ALLE Major-NC-Findings (Wirksamkeitsnachweis pro Control) - Row 30 / F-012 / 1.5.2 (Review baut auf Wirksamkeitsdaten) Querverweise: - Row 4 / F-General (AL3-Niveau) - Row 6 / F-General (Workflow-Wirksamkeit) - Row 52 / F-034 / 5.2.6 (Pentest als Wirksamkeitsnachweis) | O29: Policy Framework: - RL Wirksamkeitsmessung & Control-Verifikation - Control-Compliance-Framework (CCF) mit: · Test-Plan je Control (Frequenz, Methode, Evidenz) · Mapping Control → KPI → Verantwortlicher → Auditfile-Pfad - Monats- und Quartals-Cockpit Standards: - ISO/IEC 27001:2022 §9.1 (Monitoring, Measurement, Analysis, Evaluation) - ISO/IEC 27004 (ISMS-Metriken) - ENX VDA ISA 6.0.3 — AL3 verlangt 'aktive Verifikation', nicht nur Plausibilität Regulatorisch: - NIS-2 Art. 21(2)(b) (Wirksamkeitsbewertung) Weitere Empfehlungen: - AL3-KERN: Effektivitätsnachweise pro Major-NC-Control vor Juni-Audit - Stichprobenprüfung 10 % je Quartal - Wirksamkeits-Reporting im Management Review verankern | P29: All | Q29: Alle | R29: Hoch | S29: Offen | T29: 46173 | W29: 1
A30: F-012 | B30: Information Security | C30: IS Policies and Organization | D30: 1.5.2 | E30: To what extent is the ISMS reviewed by an independent authority? | F30: Inwieweit wird das ISMS von einer unabhängigen Behörde überprüft? | G30: Observation | H30: Der Review des ISMS bedetuet nicht nur durch eine bestimmte Auditinstanz. Der Review kann durch verschiedenste Nachweise dargegstellt werden. Kundenaudits können auch verwendet werden, ISMS wurde dadruch ggf. schon in Teile auditiert. Ggf. extern auditieren. Muss keine Organisatation/Unternehmen sein. AL2 Zertifizierung ; Pentesting ext. vom TÜV für Teile vom Katalog. Nachweise für Teilüberprüfungen oder Gesamtüberprüfungen in Teilen des TISAX 6.0n Prüfkataloges. Ext. Nachweis durch einen Externen. | J30: 4 | K30: =IF(AND(ISNUMBER(I30),ISNUMBER(J30)),J30-I30,"") | L30: Erstellung einer jährlichen ISMS Audit-Summary die man als Nachweis für den jährlichen ISMS-Audit benutzen kann. Ablage mit Nachweisen im ISMS und jährlichen 2. Sicherheitsreports per Ende Jahr. | M30: Umsetzungsgegenstand: Jährliche ISMS-Audit-Summary, die externe Nachweise (Kundenaudits, AL2-Zertifikat, Pentests durch TÜV/Externen) als unabhängige Reviews bündelt. Prozessbezug: VDA ISA 1.5.2; ISO 27001 Clause 9.2 + 9.3. Workflow Items: 1. Erfassung aller externen Audits/Pentests/Kundenaudits (Owner: ISB). 2. Jährliche ISMS-Audit-Summary mit VDA-ISA-Kapitel-Mapping. 3. Halbjährlicher Sicherheitsreport an GL. Nachweis: Audit-Summary, externe Auditberichte, Management-Review-Protokoll. Abhängigkeiten (Detail s. Spalte N): → baut auf F-002/F-011/F-003 (ISB-Unabhängigkeit) | N30: Vorgelagert: - Row 11 / F-002 / 1.2.1 (Auditprogramm) - Row 29 / F-011 / 1.5.1 (Wirksamkeitsdaten) - Row 16 / F-003 / 1.2.2 (ISB-Unabhängigkeit) Nachgelagert: - ISMS Management Review (jährlich) Querverweise: - Row 12 / F-002 / 1.2.1 (KPIs als Review-Eingang) | O30: Policy Framework: - RL ISMS-Review & Management-Bewertung - Charter unabhängige Audit-Funktion (interne Revision ODER externer Reviewer) - Jahres-Audit-Summary-Template Standards: - ISO/IEC 27001:2022 §9.2, §9.3 - ISO 19011:2018 - VDA ISA 6.0.3 Kap. 1.5.2 Weitere Empfehlungen: - Rotierende Auditoren über Standorte (DE → AT → SK → PL) - Externer Reviewer alle 3 Jahre für AL3-Konformität - Management Review mit dokumentierten Beschlüssen (PDCA-Closure) | P30: All | Q30: Alle | R30: Mittel | S30: Offen | T30: 46173 | W30: 1
A31: F-013 | B31: Information Security | C31: IS Policies and Organization | D31: 1.6.1 | E31: To what extent are information security relevant events or observations reported? | F31: Inwieweit werden informationssicherheitsrelevante Ereignisse oder Beobachtungen gemeldet? | G31: Major NC | H31: Wie werden Ereignisse gemeldet, wer kann ein Sicherheitsvorfall melden und wie macht er das. ist das kommuniziert und ging das an alle per Schulung raus? Wie wurden die REUTIB Mitarbeiter verpflichtet relevante Ereignisse zu melden. Es muss mindestens 2 Kanäle geben, nur Tiket alleine reicht nicht. es muss eine zentrale erreichbare Telefonnummer geben. Wie ist geregelt das man die Kundenverträge einhält, in denen ist ggf. geregelt das man ein Vorfall auch an die Kunden oder andere externe stakeholder melden muss. (Drohne über Werk, oder jmd. steht am Zaun, z.b), auch für OT in der Produktionslinie -> Schichtleiter. Wo schlägt die Meldung als erstes auf, wie schnell muss reagiert werden und wer ist das dann bzw. kann er das dann richtig eintakten zu der jeweiligen richtigen Abteilung ? ( Vorfall könnte auch sein das z.b hohe Schwellwerte bei den Maschinen erreicht werden) Rauchabzug könnte auch ein Bsp. sein oder Personal macht Fotos von Zeichnungen. (Selbst mal mit der Drohne testen ob sowas aufschlagen würde) Meldezeiten wie vorgegeben berücksichtigen, gilt alles auch für OT ! inkl. OLAs für Melde- Weiterleitungszeiten. Aufgrund der Überwachung (XDR Sophos und Trashhold) gleiche Meldung als Sec.Incident. | I31: 2 | J31: 3 | K31: =IF(AND(ISNUMBER(I31),ISNUMBER(J31)),J31-I31,"") -> 1 | L31: Anpassung und Implementierung des Incident Response Mgmt. Prozesses für REUTIB gesamt (inkl. OT). Ticketing, Telefonnummer und auch XDR Incidents berücksichtigen. | M31: Umsetzungsgegenstand: Mehrkanaliges Meldewesen (Ticket + 24/7-Notrufnummer + XDR-Sophos-Alerts) inkl. Kunden-Notify-Trigger und definierter Reaktionszeiten auch für OT (Schichtleiter). Prozessbezug: VDA ISA 1.6.1; ISO 27001 A.5.24; NIS-2 Art. 23. Workflow Items: 1. RL Incident Reporting (Owner: ISB). 2. Zentrale Notrufnummer (24/7) + Mailbox. 3. Integration XDR-Sophos-Alerts in Ticketing. 4. OEM-Vertragsanalyse → Kunden-Notify-Liste mit Thresholds. 5. Training aller MA (DE/AT/SK/PL). 6. Wirksamkeitstest (Drohnen-/Foto-/Zaun-Szenario). Nachweis: RL, Trainings, Simulationsbericht, Live-Tickets. Abhängigkeiten (Detail s. Spalte N): → Major NC; baut auf F-002/F-032/F-031; treibt F-014/F-015 | N31: Vorgelagert: - Row 10 / F-002 / 1.2.1 (Incident-Mgmt-Grundlage) - Row 50 / F-032 / 5.2.4 (Logging als Detektionsquelle) - Row 49 / F-031 / 5.2.3 (Malware-Schutz/MDR) Nachgelagert: - Row 32 / F-014 / 1.6.2 (OEM-Kommunikation) - Row 33 / F-015 / 1.6.3 (Krise/BCM) Querverweise: - Row 2 / F-General (Play-Ransomware Lessons-Learned) - Row 36 / F-018 / 2.1.3 (TTT-Phase 4 'Reagieren') | O31: Policy Framework: - RL Sicherheits-Incident-Meldewesen & Eskalation - 24/7-Erreichbarkeitskonzept (interne Notrufnummer + externer SOC-Vertrag) - IR-Klassifikationsmatrix (Severity 1-4) mit Reaktionszeiten Standards: - ISO/IEC 27001:2022 A.5.24-A.5.28 - ISO/IEC 27035 (vollständige Reihe) - NIST SP 800-61r2 - VDA ISA 6.0.3 Kap. 1.6.1 Regulatorisch: - NIS-2 Art. 23 (24h Frühwarnung / 72h Meldung / 1 Monat Abschluss) - DSGVO Art. 33 (72h Meldung an Aufsichtsbehörde) Weitere Empfehlungen: - Major NC: Reaktionszeiten + Eskalationskette vor AL3-Audit dokumentiert + getestet - Sophos XDR als Detektionsquelle in IR-Workflow integrieren - Mitarbeiterkommunikation: Awareness-Plakate 'Wie melde ich einen Sicherheitsvorfall?' DE/EN/SK/PL | P31: All + GL | Q31: Alle | R31: Hoch | S31: Offen | T31: 46173 | W31: 1
A32: F-014 | B32: Information Security | C32: IS Policies and Organization | D32: 1.6.2 | E32: To what extent are reported security events managed? | F32: Inwieweit werden gemeldete Sicherheitsereignisse verwaltet? | G32: Minor NC | H32: 1.6.2. haben wir mit 1.6.1 beantwortet. Verwaltung der Meldungen auch analog Kundenvertrag oder Kunden-Anforderungs-Liste. Welche Kunde will ab welchem Level von Incident informationen haben Wer ist verantwortlich für OT und IT wenn getrennt in den Meldewegen und wie läuft analog (should) Koordination der Incidents?, inkl. physische Sicherheit (Facilitmgmt.) | I32: 2 | J32: 3 | K32: =IF(AND(ISNUMBER(I32),ISNUMBER(J32)),J32-I32,"") -> 1 | L32: Implementierung/Erweiterung des Incident Response Mgmt. Prozesses für OEM-Kommunikation (etc.). Integration in das Krisenmanagement für Entscheidung für OEM Kommunkation. Bitte beachten: Very High Availability, bitte die Referenz betrachten. Bitte die Vertragswerke der OEMs betrachten -> Kundeninformation (Betrachtung erfolgt und in Prozessen abgebildet?) | M32: Umsetzungsgegenstand: Erweiterung Incident-Management um OEM-spezifischen Kunden-Notify-Workflow und Koordination IT/OT/Facility im Krisenmanagement (Very High Availability-Referenz beachten). Prozessbezug: VDA ISA 1.6.2; OEM-Vertragsanforderungen; ISO 27001 A.5.5. Workflow Items: 1. STD OEM-Kommunikation (Owner: ISB + Sales + Krisenstab). 2. Kundenmatrix: Kunde × Incident-Threshold × Notify-Frist × Kommunikationskanal. 3. Integration in Krisenstab-Entscheidungslogik. Nachweis: STD, Kundenmatrix, Entscheidungsprotokolle aus Übung. Abhängigkeiten (Detail s. Spalte N): → baut auf F-013; nutzt F-028 (Verschlüsselung) | N32: Vorgelagert: - Row 31 / F-013 / 1.6.1 (Incident Meldewesen) Nachgelagert: - Row 33 / F-015 / 1.6.3 (Krisen-Kommunikation) Querverweise: - Row 2 / F-General (Play-Ransomware: OEM-Kommunikation-Lessons) - Row 46 / F-028 / 5.1.2 (verschlüsselte Kommunikation mit OEM) | O32: Policy Framework: - OEM-Incident-Kommunikationsplan (pro Großkunde) - Vorlagen 'Initial Notification' / 'Status Update' / 'Closure Report' - Kontaktverzeichnis OEM-Security-Teams (mit Aktualisierungsverpflichtung) Standards: - ISO/IEC 27001:2022 A.5.5 (Kontakt mit Behörden, Interessensvertretern) - VDA ISA 6.0.3 Kap. 1.6.2 - TISAX 'IS-Awareness im Liefernetzwerk' Weitere Empfehlungen: - Pflicht-Klausel in OEM-Verträgen: Meldewege & Fristen prüfen - Krisenkommunikations-Übung mit fiktivem OEM-Szenario - Sprachregelung mit Marketing/Legal abgestimmt | P32: Krisenmanagement | Q32: Alle | R32: Mittel | S32: Offen | T32: 46173 | W32: 1
A33: F-015 | B33: Information Security | C33: IS Policies and Organization | D33: 1.6.3 | E33: To what extent is the organization prepared to handle crisis situations? | F33: Inwieweit ist die Organisation darauf vorbereitet, Krisensituationen zu bewältigen? | G33: Minor NC | H33: Ab wann sprechen wir von einer Krise, was ist der Auslöser für eine Krise. Wann wird das “Team” kontaktiert und wie? Wir haben noch keine Notfall und Krisenstabsorganisation. Problem-Emergency-Crisis als Rangfolge. Doku auch ausgedruckt vorhanden und die information wo dies gefunden werden kann. Notfall Laptop für Krisenstab. Übung, Testlauf. Mitarbeiter frage: Ab wann sprechen wir von einer Krise, wissen sie das? Was sind die Kritischen Geschäftsprozesse und wo stehen die. Sind dort Dinge in Abhängigkeit benötigt die wir als Ersatzvorhalten (Steuerung, Ersatzteil, Switch,). Übungen! Auslöser und Schwellwert für Krise. Notfall- und Krisenteam Aufbau, Schulung und Planung fehlt aktuell ist aber in der Planung. Definition vom Team und Ausdrucken und Notfallnotebooks mit USB-Sticks. Folgefragen: Top-Down Ansatz bis runter in OT für Verantwortlichkeiten mit BIA/GAP-Analyse; Ausfallkompomenten in Spare IT/OT (e.g. zentraler Switch...) -> DR-Spare Systems, Plan für Excercisees und Maßnahmen daraus. | I33: 2 | J33: 3 | K33: =IF(AND(ISNUMBER(I33),ISNUMBER(J33)),J33-I33,"") -> 1 | L33: Prozess für Krisenmanagement anpassen/aufbauen/schulen und üben etc. (s.l.). Wichtig; Very High Availibilty: '+ Crisis exercises and simulations involving all relevant persons, decision makers are conducted regularly. (A) | M33: Umsetzungsgegenstand: Vollständiges Notfall- und Krisenmanagement (Problem-Emergency-Crisis) mit BIA, Schwellwertdefinition, Krisenstab-Organisation, Notfallausstattung und regelmäßigen Übungen — AL3-Kernanforderung (Very High Availability). Prozessbezug: VDA ISA 1.6.3 + 5.2.8; BSI-Standard 200-4; ISO 22301. Workflow Items: 1. Krisenmanagement-RL (Owner: ISB + Krisenstab). 2. BIA/Gap-Analyse alle Standorte → kritische Geschäftsprozesse + Ersatzkomponenten (Switch, SPS, Ersatzteile). 3. Krisenstab-Organigramm + Schulung + Erreichbarkeitsliste. 4. Notfallpaket: Offline-Dokumentation, Notfall-Laptop, USB-Stick. 5. Jährliches Übungsprogramm (Tabletop + technische Recovery-Tests). 6. MA-Awareness 'Ab wann ist es eine Krise?'. Nachweis: RL, BIA-Bericht, Übungsprotokolle, Trainingsnachweise. Abhängigkeiten (Detail s. Spalte N): → baut auf F-013/F-010; treibt F-036/F-037 (BCM-Audit-Evidenz) | N33: Vorgelagert: - Row 31 / F-013 / 1.6.1 (Incident) - Row 28 / F-010 / 1.4.1 (Risiko/BIA als BCM-Eingang) Nachgelagert: - Row 54 / F-036 / 5.2.8 (BCM/DR-Tests) - Row 55 / F-037 / 5.2.9 (Backup als Wiederanlaufgrundlage) Querverweise: - Row 2 / F-General (Play-Ransomware: Krise-Eskalation) - Row 38 / F-020 / 3.1.1 (Physische Krisen) | O33: Policy Framework: - RL Business Continuity Management (BCM) - Krisenmanagement-Handbuch mit Krisenstab-Charta - BIA (Business Impact Analysis) je Werk DE/AT/SK/PL mit RTO/RPO - DR-Pläne je kritischem System Standards: - ISO 22301:2019 (BCM) - ISO/IEC 27031 (ICT-Readiness) - BSI-Standard 200-4 (BCM-Methodik) - VDA ISA 6.0.3 Kap. 1.6.3 Regulatorisch: - NIS-2 Art. 21(2)(c) Weitere Empfehlungen: - BCM-Integration ins ISMS (gemeinsame Audit-Evidenz für AL3) - Krisenstab-Übung 2026 vor Hauptaudit (Tabletop) - Alternative Standorte / Cross-Site-Backup-Strategie | P33: Krisenstabsorganisation und Prozess, ISB, Beteiligte | Q33: Alle | R33: Mittel | S33: Offen | T33: 46173 | W33: 1
A34: F-016 | B34: Information Security | C34: Human Resources | D34: 2.1.1 | E34: To what extent is the qualification of employees for sensitive work fields ensured? | F34: Inwieweit wird die Qualifikation der Mitarbeiter für sensible Arbeitsbereiche gewährleistet? | G34: Observation | H34: Gibt es eine zentrale HR, wie wird der Prozess auf die Regionen runtergebrochen? Wir wird das auf regionale HR´s runtergebrochen. Führungszeugnis, Strafregisterauszug oder Sicherheitsüberprüfung ? Wie ist es bei überlassen Mitarbeiter (Leiharbeiter) wie ist das in Thema dann in den Verträgen der “Zeitarbeitsfirma” hinterlegt. Backgroundscreening z.B Vorgaben für Anforderungen und Evidenzen liegen in Policy vor Spezifische Anforderungen wie beim Strafregisterauszug etc. für B- und C-Level Anforderungen REUTIB inkl Geheimhaltung (NDA, Backgroundscreen für REUTIB durch Partner). | I34: 3 | J34: 3 | K34: =IF(AND(ISNUMBER(I34),ISNUMBER(J34)),J34-I34,"") -> 0 | L34: Aktuell existiert nur die HR Personel Safety & Security Policy, Standards für regionale Anforderungen etablieren. | M34: Umsetzungsgegenstand: Standortspezifische HR-Standards für Background-Checks (Führungszeugnis, Strafregisterauszug, Sicherheitsüberprüfung) inkl. Regelungen für Leiharbeiter und B-/C-Level-Funktionen. Prozessbezug: VDA ISA 2.1.1; ISO 27001 A.6.1. Workflow Items: 1. STD HR-Background-Check pro Land DE/AT/SK/PL (Owner: HR + lokaler HR-Lead). 2. Erweiterung HR Personnel Safety & Security Policy um Leiharbeiterregelung (Klauseln im Vertrag der Zeitarbeitsfirma). 3. NDA-Standardprozess für Onboarding (REUTIB-Backgroundscreen durch Partner). Nachweis: HR-STD pro Standort, Stichprobe Personalakte (anonymisiert), Zeitarbeitsvertragsklauseln. Abhängigkeiten (Detail s. Spalte N): → Voraussetzung für F-017, F-023, F-025, F-045 | N34: Vorgelagert: - keine (HR-Grundprozess) Nachgelagert: - Row 35 / F-017 / 2.1.2 (Arbeitsvertrag-Klauseln) - Row 41 / F-023 / 4.1.1 (Badge-Lifecycle) - Row 43 / F-025 / 4.1.3 (Account-Lifecycle) - Row 63 / F-045 / 7.1.2 (Datenschutz-HR-Prozess) Querverweise: - Row 36 / F-018 / 2.1.3 (Schulungs-Onboarding) | O34: Policy Framework: - RL HR-Sicherheit (Onboarding / Offboarding / Rollenwechsel) - Background-Check-Verfahren je Risikoklasse (Standard / Sensitiv / Kritisch) - Joiner-Mover-Leaver-Workflow (JML) Standards: - ISO/IEC 27001:2022 A.6.1, A.6.5, A.6.6 - VDA ISA 6.0.3 Kap. 2.1.1 Regulatorisch: - DSGVO Art. 6, 9 (Background-Check) - länderspezifisches Arbeitsrecht DE/AT/SK/PL beachten Weitere Empfehlungen: - Zentrale HR-Koordination mit lokalen HR-Kontakten je Werk - Vier-Augen-Prinzip beim Offboarding - JML-Tickets als Pflicht-Nachweis | P34: HR | Q34: Alle | R34: Mittel | S34: Offen | W34: 1
A35: F-017 | B35: Information Security | C35: Human Resources | D35: 2.1.2 | E35: To what extent is all staff contractually bound to comply with information security policies? | F35: Inwieweit sind alle Mitarbeiter vertraglich verpflichtet, Informationssicherheitsrichtlinien einzuhalten? | G35: Observation | H35: Arbeitsvertrag muss entspr. Vereinbarungen (wie Geheimhaltung beinhalten), bitte vertragliche Vorlage anschauen für PL und SK), Beispiel: External Sorting e.g. (wie sind die Verträge gestaltet für SK, ggfs. PL) | I35: 3 | J35: 3 | K35: =IF(AND(ISNUMBER(I35),ISNUMBER(J35)),J35-I35,"") -> 0 | L35: Arbeitsvertag Vorlage bereitstellen | M35: Umsetzungsgegenstand: Lokale Arbeitsvertrags-Vorlagen DE/AT/SK/PL mit IS-Pflichtklauseln (Geheimhaltung, Asset-Rückgabe, Schulungspflicht, Disziplinarverfahren). Prozessbezug: VDA ISA 2.1.2; ISO 27001 A.6.2. Workflow Items: 1. Vertragsvorlagen-Review (Owner: HR + Legal + ISB). 2. Anpassung SK/PL (z. B. External Sorting). 3. Approval Legal, Roll-out HR. Nachweis: freigegebene Vertragsvorlagen je Land, HR-Reportauszug. Abhängigkeiten (Detail s. Spalte N): → baut auf F-001/F-016/F-043 | N35: Vorgelagert: - Row 7 / F-001 / 1.1.1 (Policy-Framework als Inhaltsquelle) - Row 61 / F-043 / 6.1.2 (NDA-Lifecycle) - Row 34 / F-016 / 2.1.1 (HR-Prozess) Nachgelagert: - Row 37 / F-019 / 2.1.4 (Remote-Work-Klauseln) Querverweise: - Row 9 / F-001 / 1.1.1 (Klassifikation in Klauseln) | O35: Policy Framework: - Arbeitsvertrags-IS-Klauseln (Geheimhaltung, IT-Nutzung, Disziplinarmaßnahmen) - Anlage 'IS-Verpflichtung' je Mitarbeiter - Betriebsvereinbarungen lokal (DE/AT/SK/PL) Standards: - ISO/IEC 27001:2022 A.6.2, A.6.4 - VDA ISA 6.0.3 Kap. 2.1.2 Regulatorisch: - DSGVO Art. 88 (Beschäftigtendatenschutz) - länderspezifisches Arbeitsrecht Weitere Empfehlungen: - Juristische Prüfung Klauseln in 4 Sprachen / Rechtsräumen - Disziplinar-Verfahren bei IS-Verstößen schriftlich fixieren | S35: Offen | W35: 1
A36: F-018 | B36: Information Security | C36: Human Resources | D36: 2.1.3 | E36: To what extent is staff made aware of and trained with respect to the risks arising from the handling of information? | F36: Inwieweit wird das Personal über die Risiken hinsichtlich des Umgangs mit Informationen informiert und darin geschult? | G36: Minor NC | H36: Keine Schulungen mit dem TISAX Fpkus, kein Schulungskonzept das einheitlich ist. HR wird gefragt wer hat welche Schulung gemacht. Zeig mir wie du den neuen Mitarbeitern im Hinblick auf z.b. Compliance Themen der Informationssicherheit geschult haben oder das verhalten bei auftreten von einem Schherheitsvorfall. Wie stellen wir sicher das die polnische Mitarbeiterin den gleichen Kenntnisstand wie die slowakische MA hat? Nachweis von der Schulung und von dem Onboarding, was wurde geschult und wer hat es gemacht? Wie stellen wir sicher das Informationen die neu geteilt wurden bei neuen Mitarbeitern direkt in das Onboarding kommen. Ggf. Schulungen trennen für User und für personen die keinen systemuser bekommen wobei das schwer ist da auch nicht user ggf. maschinen bedienen. Schulung über jeder Richtlinie (DOS und Don'ts), Schulungskonzept, gleicher Kenntnisstand über alle Lokationen. Teilnehmerliste und Nachweise. Bereichsbezogene Schulungen für User, Non-User, etc. -> HR ist hier im Driver. Lernakademie muss von HR getracked und adressiert werden. Auditorfragen: Direkt an HR für Nachweise für erfolgte Schulungen und Teilnahme.. | I36: 2 | J36: 3 | K36: =IF(AND(ISNUMBER(I36),ISNUMBER(J36)),J36-I36,"") -> 1 | L36: Einheitliche Schulung/Training über Länder hinweg, und HR Governance imkl. Trainingsdokumentation und Wirksamkeitsnachweis. | M36: Umsetzungsgegenstand: Einheitliches, mehrsprachiges, rollenbasiertes Awareness-Programm (User / Non-User / OT) mit Onboarding, Refresher, Compliance-Themen, zentraler Lernakademie und Wirksamkeitsnachweis — HR im Driver. Prozessbezug: VDA ISA 2.1.3; ISO 27001 A.6.3; TTT-Konzept REUTIB. Workflow Items: 1. TTT-Konzept finalisieren und C-Level-Approval (Owner: ISB). 2. Schulungsmatrix Rolle × Standort × Sprache. 3. HR-Lernakademie als zentrales Tracking-System. 4. Trainings je Richtlinie (Do/Don't-Inhalte). 5. Phishing-/Wirksamkeitstests. Nachweis: Trainingsmatrix, Teilnahmenachweise (HR direkt auditierbar), Wirksamkeitstests. Abhängigkeiten (Detail s. Spalte N): → baut auf F-001/F-002/F-General/F-011; betrifft ALLE Process Owner | N36: Vorgelagert (zwingend): - Row 7 / F-001 / 1.1.1 (Policy-Framework als Schulungsinhalt) - Row 12 / F-002 / 1.2.1 (KPIs für Trainings-Abdeckung) - Row 6 / F-General (Workflow-Wirksamkeit für ML3) - Row 29 / F-011 / 1.5.1 (Wirksamkeit) Nachgelagert: - ALLE Findings mit Process-Owner-Verantwortlichkeit (Schulung als Wirksamkeitsnachweis) Querverweise: - Row 31 / F-013 / 1.6.1 (Incident-Reporting-Schulung) - Row 17 / F-003 / 1.2.2 (Projektleiter-Schulung) - Row 24 / F-007 / 1.3.2 (BYOD-Awareness) | O36: Policy Framework: - Master-Schulungs- und Awareness-Konzept (Phase 1: Pilot Plant DE → Phase 5: Rollout SK/PL) - Trainer-Handbuch mit modularen Pflicht-Inhalten - Schulungs-Tracking (LMS) mit Nachweisen je Mitarbeiter Standards: - ISO/IEC 27001:2022 §7.2, §7.3, A.6.3 - ISO/IEC 27001 §7.4 (Communication) - VDA ISA 6.0.3 Kap. 2.1.3 Regulatorisch: - NIS-2 Art. 20(2) (Schulung Leitung) - NIS-2 Art. 21(2)(g) (Cyberhygiene-Praktiken) Weitere Empfehlungen: - KRITISCH: C-Level-Approval-Meeting (30 Min) zeitnah ansetzen - Backup-Plan bei Ablehnung: gestufter Rollout DE-only zur AL3-Demonstration - Trainings-KPI ≥ 95 % Abdeckung pro Standort vor Hauptaudit - Schulungsmaterial 4-sprachig (DE/EN/SK/PL) | P36: HR | Q36: Alle | R36: Mittel | S36: Offen | W36: 1
A37: F-019 | B37: Information Security | C37: Human Resources | D37: 2.1.4 | E37: To what extent is mobile work regulated? | F37: Inwieweit ist mobile Arbeit reguliert? | G37: Minor NC | H37: Beispiel auf Geschäftsreisen: Wie ist die Vorgabe wenn du in ein kritischen Land wie China reist. Gilt inzwischen auch schon für USA. Mitarbeiter dürfen nur ins Homeoffice nach Schulung der Richtlinie. Diese muss auch von Mitarbeiter unterschrieben werden. Sind dem Mitarbeiter die absuluten “no-Go´s” klar? Und könnten einige davon aufzählen? Beispiel: es dürfen keine cloud dienste verwendet werden aber verschicken dann die Schicht Pläne untereinander per WhatsApp. Ist Verständnis z.B. dafür da was “cloud” bedeutet? Anlehnung an Diskussion vom 20.4.26 im StageReview (Drucken im HomeOffice); Reisetätigkeiten und Bitlocker (Device Encryption); Richtlinie für Remote Work inkl. Training (aktuell im Asset Mgmt. Policy) und vom MA unterzeichnet im Arbeitsvertrag (beinhaltet). -> Internal Awareness | I37: 2 | J37: 3 | K37: =IF(AND(ISNUMBER(I37),ISNUMBER(J37)),J37-I37,"") -> 1 | L37: Remote Working Policy erstellen, inklusive Standards für Regionen und der Vorgaben auch für HR. Device Encryption und Training/Schulung der MA durch HR, inkl. Fokus für No-Go's | M37: Umsetzungsgegenstand: Dedizierte Remote-Work-Policy inkl. Reiserichtlinien (kritische Länder CN/USA), Drucken im Home-Office, Bitlocker/Device Encryption, unterschriebener MA-Verpflichtung und No-Go-Awareness (z. B. Cloud-Versand von Schichtplänen via WhatsApp). Prozessbezug: VDA ISA 2.1.4; ISO 27001 A.6.7, A.7.9. Workflow Items: 1. RL Remote Work (Owner: ISB + HR). 2. STD Reisesicherheit (Owner: HR + Legal): Gerätekonfiguration, Datenklassifikation, VPN-Pflicht. 3. Device-Encryption-Standard (Bitlocker) + Compliance-Check. 4. Awareness-Modul 'No-Go-Liste'. 5. Unterschriebene MA-Verpflichtung im Arbeitsvertrag. Nachweis: RL, STD, unterschriebene Verpflichtungen, Compliance-Reports. Abhängigkeiten (Detail s. Spalte N): → baut auf F-007/F-022/F-017; treibt F-024/F-026 | N37: Vorgelagert: - Row 24 / F-007 / 1.3.2 (Private Geräte) - Row 40 / F-022 / 3.1.4 (Mobile Geräte) - Row 35 / F-017 / 2.1.2 (Arbeitsvertrag-Klauseln) Nachgelagert: - Row 42 / F-024 / 4.1.2 (MFA für Remote) - Row 44 / F-026 / 4.2.1 (Konditionaler Zugriff) Querverweise: - Row 9 / F-001 / 1.1.1 (Klassifikation auf Reisen) | O37: Policy Framework: - RL Mobile Work / Remote Work / Geschäftsreisen - Sichtschutz-Verfahren (z. B. Bildschirmfilter Pflicht in öffentlichen Räumen) - Reise-Briefing für sensitive Auslandsreisen (Hochrisiko-Länder) Standards: - ISO/IEC 27001:2022 A.6.7 (Remote Working) - BSI Baustein SYS.4.5 (Mobile Devices) - VDA ISA 6.0.3 Kap. 2.1.4 Weitere Empfehlungen: - Conditional Access für Geo-Risikoländer aktivieren - VPN-Pflicht außerhalb des Unternehmensnetzwerks - Awareness-Modul Reisen (TTT-Phase 2) | P37: HR | Q37: Alle | R37: Mittel | S37: Offen | W37: 1
A38: F-020 | B38: Information Security | C38: Physical Security | D38: 3.1.1 | E38: To what extent are security zones managed to protect information assets? | F38: Inwieweit werden Sicherheitszonen verwaltet, um Informationsressourcen zu schützen? | G38: Major NC | H38: Können die Sicherheitszonen Gebäude Layout gezeigt werden und ist dieser aktuell? Wenn der Auditor in eine “rote” zone gehen würde, würde das gehen oder wie ist der Ablauf. Beispiel auch anhand Graz. Besucherregelung? Sobald im Büro dann im Entwicklungsbereich. Personal, die Management Bereiche, ggf. Vertrieb da wo Angebote liegen sowie die Serveräume. REUTIB benötigt für jeden Standort ein Sicherheitskonzept, egal wie groß. Kann die Türe offen gelassen werden, wenn ja gibt es ein Alarm? Wer verwaltet die Zugangs-Chips. Wievile Zugangs-Chips / Schlüssel wurden ausgegebe, die die Türe öffnen können. Was passiert wenn ein Chip/Badge verloren geht? Wer meldet wohin und ist sichergestellt das dieser Chip unverzüglich deaktiviert wird. Kann das Facility Mgmt in den Raum und wenn dieser extern ist, gibt es ein Vertrag und eine Regelung über den Zutritt? Wie wird sichergestellt das vertrauliche Meetings nicht von anderen Mitbekommen werden auch in Bezug auf mithören oder durch eine Scheibe schauen (e.g. Graz Hauptraum -> Glasinnenfenster. Selbst wenn es um Entwicklungsdiskussionen geht Netzwerkkomponenten müssen geschützt werden und dürfen nicht offen zugänglich sein in (e.g.) Meetingräumen oder Druckbereichen. | I38: 1 | J38: 3 | K38: =IF(AND(ISNUMBER(I38),ISNUMBER(J38)),J38-I38,"") -> 2 | L38: Erstellung und Etablierung eines Sicherheitszonenkonzeptes Facility Mgmt. Physische Sicherheit und HR. Unterscheidung im Zutritt für Zonen, Serverräume, Development (wenn isoliert), Zutrittsabsicherung (e.g. Graz), Thema Besucherregelung, SK und PL zu prüfen. Fragen (e.g. für Graz): Kann die Zugangstüre theoretisch offen bleiben?, Alarmauslösung bei offener Türe, Share Environment (Graz): Zentrales Facilimgmt. und Prozess für Verwaltung der Chips (Prozess), Bischofshofen: Div. Türen, Zugriff auf Daten und Whiteboard im Eingangsraum, Organisatorische Vorgaben, Darstellung über Facilitmgmt. Sicherheitszone Graz muss beschrieben sein, e.g. wenn keine Person im Raum ist. Sicherheitskonzept pro Standort Erweiterung des Zonenkonzeptes für jeden Standort (!) Drucker in Serverraum (no go) Besprechungen mit Engineeringdaten für Confidential Dokumente nur in abhörsicheren Räumen die geschlossen sind. | M38: Umsetzungsgegenstand: Sicherheitszonen-Konzept je Standort (DE/AT/SK/PL) inkl. Zonen-Layout, Zugangslogik, Besucherregelung, Chip-/Schlüsselverwaltung, akustischer/visueller Vertraulichkeitsschutz und Schutz Netzwerkkomponenten. Prozessbezug: VDA ISA 3.1.1; ISO 27001 A.7.1–A.7.6; OEM-Prototype-Protection. Workflow Items: 1. Zonenkonzept pro Standort (Owner: ISB + Facility + Plant Manager). 2. Chip-/Schlüssel-Verwaltungsprozess (Ausgabe, Verlust, Rückgabe). 3. Alarm-/Türkontrolllogik bei offener Tür. 4. Besucherregelung mit Begleitpflicht. 5. Glaswand-/Sicht-/Akustikschutz für vertrauliche Räume (z. B. Graz Hauptraum). 6. Drucker aus Serverräumen entfernen (No-Go). Nachweis: Zonenpläne je Standort, FM-Prozessdoku, Chip-Audit, Begehungsprotokoll. Abhängigkeiten (Detail s. Spalte N): → Major NC; baut auf F-006; treibt F-023/F-035 | N38: Vorgelagert: - Row 23 / F-006 / 1.3.1 (Asset-Lokationen als Schutzobjekte) Nachgelagert: - Row 41 / F-023 / 4.1.1 (Badge-System für Zonenzugang) - Row 53 / F-035 / 5.2.7 (Netzwerk-Zonen analog zu Phys.) Querverweise: - Row 33 / F-015 / 1.6.3 (BCM: physische Resilienz) - Row 14 / F-003 / 1.2.2 (OT-Schutzzonen) | O38: Policy Framework: - RL Physische Sicherheit & Zonierungskonzept - Werks-Layout je Standort mit Zonen-Tagging (Public / Operational / Sensitive / High-Sec) - Besucherregelung mit Begleitpflicht Standards: - ISO/IEC 27001:2022 A.7.1-A.7.4, A.7.6 - BSI Baustein INF.1 (Allgemeines Gebäude) - VDA Prototypenschutz-Leitfaden (mind. 4-Zonen-Modell) - VDA ISA 6.0.3 Kap. 3.1.1 Weitere Empfehlungen: - Major NC: Layout-Pläne mit Zonen-Markierung als auditreife Nachweise (alle 4 Standorte) - Foto-Dokumentation Zugangskontrollen je Werk - Begehung mit Auditor in der Vor-Audit-Phase | P38: ISB, Plant Manager, Facility Mgmt. | Q38: Alle | R38: Hoch | S38: Offen | W38: 1
A39: F-021 | B39: Information Security | C39: Physical Security | D39: 3.1.3 | E39: To what extent is the handling of supporting assets managed? | F39: Inwieweit wird der Umgang mit unterstützenden Vermögenswerten verwaltet? | G39: Minor NC | H39: Entsorgung von Dokumenten (Archiv) und Datenträger und gibt es Prüfprotokoll und Entsorgungsprotokolle, was wurde entsorgt? Wer sind die externen Entsorger? Reisswolf GmbH (DE) DE: Reisswolf Unternehmen beauftragt durch REUTIB Papierdaten, aktuell n.b. für PL, SK, AT Umsetzung analog: (e.g. ISO 21964, at least Security Level 4) | I39: 2 | J39: 3 | K39: =IF(AND(ISNUMBER(I39),ISNUMBER(J39)),J39-I39,"") -> 1 | L39: Disposal Prozess für "Papier" und Inf. Assets mit nachweisen für Entsorgung (ext. / int.). Klärung für DE -> Reisswolf, offene Klärung für AT, SK, PL Wichtig: Asset Klassifizierung -> e.g. Jahressteuer REUTIB Betrachtung Asset Mgmt. & Classification Policy für Anwendbarkeit, Aufbewarungsfrist, ggfs. Standardvorgaben für Regionen. Beispiel: Entsorgung Dokumente HR SK, Archive, Aservatenkammer etc., Buchhaltung Leutenbach, Vertrieb & Purchaising und PMO. '+ Supporting assets are protected. Disposal of supporting assets is conducted in accordance with one of the relevant standards (e.g. ISO 21964, at least Security Level 4). (C) | M39: Umsetzungsgegenstand: Standardisierung der sicheren Entsorgung von Papier und Datenträgern nach ISO 21964 (mind. Security Level 4) für alle Standorte inkl. Aufbewahrungsfristen und Entsorgungsprotokolle. Prozessbezug: VDA ISA 3.1.3 + 5.3.3; ISO 27001 A.7.10/A.7.14; ISO 21964. Workflow Items: 1. STD Disposal (Owner: ISB + Facility). 2. Dienstleisterauswahl AT/SK/PL analog Reisswolf (DE). 3. Entsorgungsprotokoll-Template + Aufbewahrungsfristen-Mapping (Steuer, HR, Engineering, PMO). 4. Asset-Klassifizierung als Eingangsfilter. Nachweis: STD, Dienstleisterverträge AT/SK/PL, Entsorgungsprotokolle (Stichprobe). Abhängigkeiten (Detail s. Spalte N): → baut auf F-006/F-008; treibt F-040; SK/PL Lücke schließen | N39: Vorgelagert: - Row 23 / F-006 / 1.3.1 (Asset-Lifecycle) - Row 25 / F-008 / 1.3.3 (externe IT-Disposal) Nachgelagert: - Row 58 / F-040 / 5.3.3 (Cloud-Disposal) Querverweise: - Row 9 / F-001 / 1.1.1 (Klassifikation als Vernichtungs-Trigger) | O39: Policy Framework: - RL Datenträger- und Dokumentenentsorgung - Vernichtungsklassen je Klassifikation (Stufe P-4 bis P-7 / O-5 nach DIN 66399) - Vernichtungsprotokoll als Pflicht-Nachweis Standards: - ISO/IEC 27001:2022 A.7.10, A.7.14 - ISO/IEC 21964 / DIN 66399 (Vernichtung) - NIST SP 800-88 (Media Sanitization) - VDA ISA 6.0.3 Kap. 3.1.3 Weitere Empfehlungen: - Bestehende DE-Lösung (Reisswolf) auf AT/SK/PL erweitern - Lokale Dienstleister mit ISO-21964-Zertifizierung wählen - Quartals-Audit Disposal-Quittungen | P39: ISB, Plant Manager, Facility Mgmt. | Q39: Alle | R39: Hoch | S39: Offen | W39: 1
A40: F-022 | B40: Information Security | C40: Physical Security | D40: 3.1.4 | E40: To what extent is the handling of mobile IT devices and mobile data storage devices managed? | F40: Inwieweit wird der Umgang mit mobilen IT-Geräten und mobilen Datenspeichergeräten verwaltet? | G40: Minor NC | H40: Können Unternehmensdaten auf privaten Geräten gespeichert werden? Sind die Assets (Geräte) registriert, die verwendet werden können? Funktionier die USB Schnittstelle? Nicht freigegebene Drucker sperren?! (geht das technisch überhaupt). Wenn wir die Geräte nicht registrieren können (private) dann dürfen keine Zugänge von nicht registrierter Geräten auf Unternehmensdaten möglich sein. (O365) Einstandsfrage: Können Unternehmensdaten auf Geräten enthalten sein? Wenn neine: Verwendung eines MDM, bzw. sind die Geräte registriert, VPN, funktioniert die USB Schnittstelle. USB-Schnittstellen funktionieren nur für normale USB-Devices außer USB-Sticks. Zugriff nur über Registerierung des Assets -> aktuell nicht erfüllt, (aktuell der Fall bei privaten Assets), | I40: 2 | J40: 3 | K40: =IF(AND(ISNUMBER(I40),ISNUMBER(J40)),J40-I40,"") -> 1 | L40: Anmerkung: Nicht freigegeben Drucker sperren (ist das umsetzbar?). Asset Klassifzierungspolicy beachten für Vorgaben (Streng- und Vertraulich) | M40: Umsetzungsgegenstand: Sicherstellung, dass Unternehmensdaten ausschließlich auf registrierten Geräten verarbeitet werden; technische Sperrung nicht freigegebener Drucker und USB-Sticks; Bezug Asset-Klassifizierungs-Policy. Prozessbezug: VDA ISA 3.1.4; ISO 27001 A.7.9, A.8.7. Workflow Items: 1. MDM/Intune-Compliance-Policy (Owner: IT-Leitung). 2. Conditional Access: Block O365 für nicht registrierte Geräte. 3. USB-Storage-Block (außer freigegebene Wechselmedien) via Endpoint-Policy. 4. Druckerfreigabe-Liste (Print-Server-Whitelist). Nachweis: MDM-Reports, CA-Policy-Export, Endpoint-Konfigurationsexport. Abhängigkeiten (Detail s. Spalte N): → baut auf F-006; treibt F-019/F-007/F-024 | N40: Vorgelagert: - Row 23 / F-006 / 1.3.1 (Asset-Mgmt: Mobile als Asset) Nachgelagert: - Row 37 / F-019 / 2.1.4 (Remote Work) - Row 24 / F-007 / 1.3.2 (Private vs. Unternehmensgerät) - Row 42 / F-024 / 4.1.2 (MFA für mobile) Querverweise: - Row 49 / F-031 / 5.2.3 (Mobile-Malware-Schutz) | O40: Policy Framework: - RL Mobile Geräte / MDM-Policy - Verfahren bei Verlust/Diebstahl (Remote-Wipe-Pflicht) - Geräte-Issue-Prozess mit Übergabeprotokoll Standards: - ISO/IEC 27001:2022 A.7.9, A.8.1 - BSI Baustein SYS.4.5 - VDA ISA 6.0.3 Kap. 3.1.4 Weitere Empfehlungen: - Intune/MDM-Compliance-Reporting als KPI - Verschlüsselungs-Pflicht (Geräte + SD-Karte) - Awareness Reise-Briefing | P40: IT, ISB | Q40: Alle | R40: Mittel | S40: Offen | W40: 1
A41: F-023 | B41: Information Security | C41: Identity and Access Management | D41: 4.1.1 | E41: To what extent is the use of identification means managed? | F41: Inwieweit wird die Verwendung von Identifikationsmitteln verwaltet? | G41: Minor NC | H41: Welche system oder Schlüssel bekomme ich um zu meinem Arbeitsplatz zu kommen. Gilt dieser Zugang dann ewig oder nur für bestimmten Zeitraum und wir reviewed? Kein Lifecycle! spätestens alle 2 Jahre muss bei der HR der Zugang erneuert werden. HR trackt dies nachweislich. Bei Leiharbeiter oder befristeten Arbeitsverträge, ggf. direkt an Vertragsende knüpfen sodas der Zugang automatisch abläuft. Es muss beschrieben und dem MA klar sein was zu tun ist wenn er den Wer ist freigeschalten für die sensiblen Bereiche und zeige mir das in einem tool. Beispiel. türe 23, wer darf alles rein? Wie ist die Rückverfolgbarkeit, wann hat wer, welche Zugriffe bekommen und wurden entfernt. Fokus: Physische Sicherheit für Arbeitsbereich, Zutrittsprozess in HR für Werksgelände, Automatischer Ablauf vom Badge und/oder Schlüssel fehlt und muss implementiert, Leiharbeiter gleiche Prozedur für Ablauf Arbeitsvertrag (Befristete Arbeitsverträge), Gibt es eine klare Beschreibung wenn der MA den Chip/Schlüssel verliert? -> Überlegung Teil der HR-Policy auch für MA Onboarding und Information. Bei physischen Schlüssel gleiche Vorgangsweise für unverzügliche Verlustanzeige. Auditorfrage: Wer darf in Türe No NN und wo ist der Prozess abgebildet (Workflow mit Klara besprechen) -> Rückverfolgbarkeit | I41: 2 | J41: 3 | K41: =IF(AND(ISNUMBER(I41),ISNUMBER(J41)),J41-I41,"") -> 1 | L41: 2 Jahre Lifecycle für Badget auch für Schlüssel | M41: Umsetzungsgegenstand: Lifecycle-Management für physische Identifikationsmittel (Badge/Schlüssel) inkl. 2-Jahres-Renewal, Befristungs-Sync mit Vertragsende, Verlustprozess und Rückverfolgbarkeit. Prozessbezug: VDA ISA 4.1.1; ISO 27001 A.5.16. Workflow Items: 1. STD Badge/Key-Lifecycle (Owner: HR + Facility + ISB). 2. HR-Trigger: befristete Verträge / Leiharbeiter → automatischer Badge-Expiry. 3. Verlustprozess mit unverzüglicher Deaktivierung + Audit-Trail. 4. Workflow Klara: 'Wer darf Türe NN' → Rückverfolgbarkeit. Nachweis: STD, Lifecycle-Reports, Verlust-Tickets, Zutrittsmatrix. Abhängigkeiten (Detail s. Spalte N): → baut auf F-016/F-020; analog zu F-025 | N41: Vorgelagert: - Row 34 / F-016 / 2.1.1 (HR-JML-Prozess) - Row 38 / F-020 / 3.1.1 (Zonierung) Nachgelagert: - Row 43 / F-025 / 4.1.3 (Account-Lifecycle analog) Querverweise: - Row 16 / F-003 / 1.2.2 (Verantwortlichkeit Sicherheitsdienst) | O41: Policy Framework: - RL Physischer Zugriff & Badge-Mgmt - Badge-Lifecycle (Antrag → Ausstellung → Anpassung → Rückgabe) - Besucherausweis-Verfahren Standards: - ISO/IEC 27001:2022 A.7.2, A.7.6 - VDA Prototypenschutz-Leitfaden - VDA ISA 6.0.3 Kap. 4.1.1 Weitere Empfehlungen: - Zonenrechte pro Rolle definiert (RBAC für Zutritt) - Quartals-Audit aktive Badges vs. aktive Mitarbeiter - Berechtigungs-Review bei Rollenwechsel innerhalb 7 Tagen | P41: IT, OT, ISB | Q41: Alle | R41: Mittel | S41: Offen | W41: 1
A42: F-024 | B42: Information Security | C42: Identity and Access Management | D42: 4.1.2 | E42: To what extent is the user access to IT services and IT systems secured? | F42: Inwieweit ist der Zugang des Nutzers zu IT-Diensten und IT-Systemen gesichert? | G42: Minor NC | H42: Wo kein MFA -> Frage: Sind dort vertrauliche Informationen hinterlegt. Wenn mit gleichem Account in der Erstanmeldung MFA erfolgt und gleicher Account im Folgesystem ohne MFA, dann gilt der MFA von der Erstanmeldung. Brute Force e.g. nur bei ext. Zugriff und vorher MFA ?! Digital Wallet (Passwort Tresor im Einsatz), Nachweis und lokal verfügbarer Tresor, Training? Umsetzung für OT? | I42: 1 | J42: 3 | K42: =IF(AND(ISNUMBER(I42),ISNUMBER(J42)),J42-I42,"") -> 2 | L42: Umsetzung OT | M42: Umsetzungsgegenstand: Vollständige MFA-Abdeckung für Systeme mit vertraulichen Informationen mit dokumentierter Risikobewertung für nicht-MFA-fähige (insbes. OT-)Systeme; Etablierung Passwort-Tresor mit Awareness. Prozessbezug: VDA ISA 4.1.2; ISO 27001 A.8.5. Workflow Items: 1. MFA-Coverage-Matrix (Owner: IT + ISB). 2. ISRA-Eintrag pro nicht-MFA-System inkl. kompensierender Kontrollen. 3. Brute-Force-Schutz für externe Zugriffe. 4. Passwort-Tresor-Roll-out + Training. 5. OT-spezifische Authentifizierung (z. B. Jump-Host mit MFA-Vorlagerung). Nachweis: MFA-Matrix, ISRA, Trainingsnachweis. Abhängigkeiten (Detail s. Spalte N): → baut auf F-010/F-001; treibt F-007/F-019/F-026/F-029 | N42: Vorgelagert: - Row 28 / F-010 / 1.4.1 (Risiko-Mgmt: MFA-Erfordernis je Schutzbedarf) - Row 9 / F-001 / 1.1.1 (Klassifikation als MFA-Trigger) Nachgelagert: - Row 24 / F-007 / 1.3.2 (private Geräte → MFA) - Row 37 / F-019 / 2.1.4 (Remote → MFA) - Row 44 / F-026 / 4.2.1 (PAM-MFA) - Row 47 / F-029 / 5.2.1 (Change-Approval-MFA) Querverweise: - Row 22 / F-005 / 1.2.4 (externe Zugriffe) | O42: Policy Framework: - RL Authentifizierung & Identitätsmanagement - MFA-Pflicht-Matrix je Schutzbedarf (Standard / Privileged / Cross-Border) - Ausnahme-Workflow bei Nicht-MFA-fähigen Systemen (kompensierende Maßnahme) Standards: - ISO/IEC 27001:2022 A.5.16, A.5.17, A.8.5 - NIST SP 800-63B (AAL2/AAL3) - VDA ISA 6.0.3 Kap. 4.1.2 Weitere Empfehlungen: - MFA-Coverage als monatliches KPI - Phishing-resistente MFA (FIDO2) für privilegierte Konten - OT-Systeme ohne MFA: kompensierende Bastion-Host-Lösung | P42: IT, OT, ISB | Q42: Alle | R42: Mittel | S42: Offen | W42: 1
A43: F-025 | B43: Information Security | C43: Identity and Access Management | D43: 4.1.3 | E43: To what extent are user accounts and login information securely managed and applied? | F43: Inwieweit werden Benutzerkonten und Login-Informationen sicher verwaltet und angewendet? | G43: Minor NC | H43: Was bedeutet das in der Umsetzung für OT? Verwendbarkeit des Shared Account nur intern verwendbar oder auch von Außen (mit Zugriff) ? IT/OT Partner Zugriff auf Shared Accounts? (prüfen, nicht zulässig) Überprüfung ob Accounts noch funktionieren, oder deaktiviert, für LP Minimaler Zugriff: Def. Zugriffsmatrix über Line Wie kommt der MA zum Benutzeraccount? (gegeben im HR Joiner Prozess) Ext. MA -> Gleicher Account wie Interner, oder anderer Bezeichnung, Klassifizierung von ext. MA, 1. Teamviewer, 2. User und Gerät, 3. Int. zu Ext. MA. Überlegung: Bezeichnung EXT in der Mail-Adresse (interessant für OEMs). | I43: 2 | J43: 3 | K43: =IF(AND(ISNUMBER(I43),ISNUMBER(J43)),J43-I43,"") -> 1 | L43: Umsetzung OT, Least Privil./Need-to-know Prinzip Umsetzung, Howto Aufbau für Teamleads etc. Bezeichnung EXT in der Mail-Adresse (interessant für OEMs). | M43: Umsetzungsgegenstand: Verbot bzw. strikte Kontrolle von Shared Accounts; Kennzeichnung externer MA-Accounts ('EXT' in UPN/Mail); Least-Privilege/Need-to-Know-Umsetzung inkl. Zugriffsmatrix; OT-Account-Lifecycle. Prozessbezug: VDA ISA 4.1.3; ISO 27001 A.8.2, A.5.18. Workflow Items: 1. Account-Standard (Owner: IT + ISB). 2. Externe MA: UPN-/Mail-Konvention ext.vorname.nachname@reutib.com. 3. Zugriffsmatrix je Line/Rolle. 4. Disable-Prozess für nicht genutzte Accounts (z. B. nach 90 Tagen). 5. Howto/Standard für Team-Leads. Nachweis: Account-Audit-Report, UPN-Liste, Zugriffsmatrix. Abhängigkeiten (Detail s. Spalte N): → baut auf F-005/F-023/F-016; treibt F-026 | N43: Vorgelagert: - Row 22 / F-005 / 1.2.4 (externe Zugriffe) - Row 41 / F-023 / 4.1.1 (Badge-Lifecycle analog) - Row 34 / F-016 / 2.1.1 (HR-JML) Nachgelagert: - Row 44 / F-026 / 4.2.1 (RBAC/PAM) Querverweise: - Row 50 / F-032 / 5.2.4 (Account-Logging) | O43: Policy Framework: - RL Account Management & EXT-Kennzeichnung externe Konten - JML-Workflow IT-Account (Joiner/Mover/Leaver) - Naming Convention: EXT_<Vendor>_<User> Standards: - ISO/IEC 27001:2022 A.5.16, A.5.18 - VDA ISA 6.0.3 Kap. 4.1.3 Weitere Empfehlungen: - Quartals-Account-Recertification (auch OT-Accounts) - Service-Accounts mit Owner und Rotation - Stale-Account-Detection (>90 Tage inaktiv) | P43: IT, OT, ISB | Q43: Alle | R43: Mittel | S43: Offen | W43: 1
A44: F-026 | B44: Information Security | C44: Identity and Access Management | D44: 4.2.1 | E44: To what extent are access rights assigned and managed? | F44: Inwieweit werden Zugriffsrechte zugewiesen und verwaltet? | G44: Minor NC | H44: Wer hat welche Berechtigungen, wer gibt es frei? Es ist egal ob OT oder File oder auf Anwendungsebene. Wer überprüft und wie ist sichergestellt das es abläuft bzw. bei Änderungen mehr oder weniger Rechte bekommt. Kann z.B. die HR im ERP Kundeninformationen oder Rechnungen einsehen? Wir müssen auch extrem auf die Projekte achten, wie ist es mit zentralen Projektordnern und kann es sein das jemand auch noch nach 3 Jahren Zugriff auf die Ordner hat? Wenn z.b. auf Teams share einladungen verschickt werden, bleibt das dann für immer? Wer ist der Verantwortliche von welchem System und wie bekommt er Änderungen in Bezug auf Rechte mit oder stellt den request? Role-based authorization (RBAC) Privileged Access Management (PAM) Just-in-Time / Just-Enough Access (elevated rights only for short periods, e.g., Local Admin for 8 hours) Lifecycle-based authorization control Info: Auditoren schauen hauptsächliche auf Dateien und Ordnerebene und Projektorganissation und der Zugriffsrechte (e.g. Teams f. Channelzugriffe etc.) | I44: 2 | J44: 3 | K44: =IF(AND(ISNUMBER(I44),ISNUMBER(J44)),J44-I44,"") -> 1 | L44: Implementierung Approval ISB für Approval von Zugriffsrechten. Umsetzung Workflow für den Verantwortlichenn SW/Tool Inhaber bei Verteilung von Rollen und Rechten -> wie ist der ISB involviert. | M44: Umsetzungsgegenstand: Rollenbasiertes Berechtigungsmodell (RBAC) mit Privileged Access Management (PAM) und Just-in-Time-Elevation, ISB-Approval-Workflow und Lifecycle-Kontrolle insbes. für Datei-/Ordner- und Projektberechtigungen (Teams-Channels). Prozessbezug: VDA ISA 4.2.1; ISO 27001 A.5.15–A.5.18, A.8.2. Workflow Items: 1. RBAC-Konzept (Owner: ISB + IT) je Anwendung. 2. PAM-Tool-Auswahl + JIT-Elevation (z. B. Local-Admin 8h-Fenster). 3. Approval-Workflow: System-Owner → ISB → IT. 4. Quartalsmäßiges Berechtigungs-Recertification (Projekte/Teams). 5. Audit-Trail für Auditor-Stichprobe (Dateien/Ordner/Teams-Channels). Nachweis: RBAC-Konzept, PAM-Logs, Recertification-Berichte. Abhängigkeiten (Detail s. Spalte N): → baut auf F-010/F-025; treibt F-005/F-029 | N44: Vorgelagert: - Row 28 / F-010 / 1.4.1 (Risiko-basiert) - Row 43 / F-025 / 4.1.3 (Account-Mgmt) Nachgelagert: - Row 22 / F-005 / 1.2.4 (externe Zugriffe → JIT/PAM) - Row 47 / F-029 / 5.2.1 (Change mit PAM) Querverweise: - Row 42 / F-024 / 4.1.2 (MFA für privilegierte Konten) | O44: Policy Framework: - RL Berechtigungsmanagement (RBAC + PAM + JIT) - Berechtigungsmodell-Doku je Anwendung (Rollen-Matrix) - Privilege Access Workflow (Antrag + Approval + Audit) Standards: - ISO/IEC 27001:2022 A.5.15, A.5.16, A.5.18, A.8.2, A.8.3, A.8.18 - NIST SP 800-53 AC-2, AC-5, AC-6 - IEC 62443-3-3 SR 2.1 (OT-Zugriffe) - VDA ISA 6.0.3 Kap. 4.2.1 Weitere Empfehlungen: - PAM-Tool-Auswahl (BeyondTrust / CyberArk / Delinea) - JIT-Default für admins (Standzeit ≤ 8h) - Session-Recording als Pflicht für externe + privilegierte Sessions | P44: IT, OT, ISB | Q44: Alle | R44: Mittel | S44: Offen | W44: 1
A45: F-027 | B45: Information Security | C45: IT(OT) Security / Cyber Security | D45: 5.1.1 | E45: To what extent is the use of cryptographic procedures managed? | F45: Inwieweit wird der Einsatz kryptografischer Verfahren gesteuert? | G45: Major NC | H45: wie wird sichergestellt das Verschlüsselung anhand der Klassifizierung stattfindet? wie stellen wir ein Notfallprozess dar zur Wiederherstellung wo beziehen wir Zertifikate und wo setzten wir überall Zertifikate ein. Wer ist für die Zertifikate verantwortlich. CA-ROOT Bank- USB Stick- unterschriftsdatei ist ggf. sogar in der cloud Wer ist die CA-Root, woher kommen die Zertifikate und wie werden die Zertifikate in welchem Prozess erneuert. Halb- und/oder Vollautomatische CA -Root mit Revoking-List. Wie sieht der Prozess aus und die Nachweise für Umsetzung für die IT. Umsetzung in OT J/N für Certificate Handling. | I45: 1 | J45: 3 | K45: =IF(AND(ISNUMBER(I45),ISNUMBER(J45)),J45-I45,"") -> 2 | L45: Siehe dazu die Ausführungen ENX im Screenshot - 2 Auditplanungen (IT und OT) ISB -> Sascha Pulver für Zertifikats-Fokus | M45: Umsetzungsgegenstand: Durchgängiges Kryptografie- und Zertifikatsmanagement mit CA-Root-Festlegung, Revocation-List, Lifecycle-Automation, Notfall-Wiederherstellungs-Prozess und getrennter Auditplanung IT/OT. Prozessbezug: VDA ISA 5.1.1; ISO 27001 A.8.24. Workflow Items: 1. RL Kryptografie & Zertifikate (Owner: ISB + IT-Lead S. Pulver). 2. Inventar aller Zertifikatseinsätze (HW, SW, Bank-USB, Cloud-Signatur, OT). 3. CA-Root-Konzept: intern vs. extern, Revocation, Renewal-Automation. 4. Notfall-Schlüsselwiederherstellung (Key Escrow). 5. Trennung Auditplanung IT/OT. Nachweis: RL, Zertifikats-Inventar, Renewal-Protokolle, Notfalltest-Bericht. Abhängigkeiten (Detail s. Spalte N): → Major NC + Krit. Prio; baut auf F-006/F-010/F-001; treibt F-028/F-024/F-026/F-037/F-041 | N45: Vorgelagert: - Row 23 / F-006 / 1.3.1 (Asset Mgmt — Krypto-Assets) - Row 28 / F-010 / 1.4.1 (Risiko-Bewertung) - Row 9 / F-001 / 1.1.1 (Klassifizierung als Trigger) Nachgelagert: - Row 46 / F-028 / 5.1.2 (operative Verschlüsselungsverfahren) - Row 42 / F-024 / 4.1.2 (MFA-Token-Verwaltung) - Row 44 / F-026 / 4.2.1 (PAM-Crypto) - Row 55 / F-037 / 5.2.9 (Backup-Verschlüsselung) - Row 59 / F-041 / 5.3.4 (Mandantentrennung Cloud) Querverweise: - Row 32 / F-014 / 1.6.2 (OEM-Kommunikation verschlüsselt) | O45: Policy Framework: - RL Kryptografie & Zertifikatsmanagement - CA-Root-Konzept inkl. Offline-Root-CA-Strategie - Key-Mgmt-Plan (Generation, Storage, Rotation, Recovery, Destruction) - Revocation-Verfahren (CRL/OCSP) Standards: - ISO/IEC 27001:2022 A.8.24 - BSI TR-02102 (Kryptographische Verfahren) - NIST SP 800-57 (Key Management) - IETF RFC 5280 (PKI) - VDA ISA 6.0.3 Kap. 5.1.1 Weitere Empfehlungen: - KRITISCHE Priorität: CA-Root-Festlegung vor allen anderen Krypto-Maßnahmen - HSM für Offline-Root-CA (oder PKI as a Service) - Crypto-Inventur (alle Zertifikate, Algorithmen, Schlüssellängen) - Post-Quantum-Crypto-Roadmap als Anhang (mittelfristig) | P45: IT, OT, ISB | Q45: Alle | R45: Kritisch | S45: Offen | W45: 1
A46: F-028 | B46: Information Security | C46: IT(OT) Security / Cyber Security | D46: 5.1.2 | E46: To what extent is information protected during transfer? | F46: Inwieweit sind Informationen während der Übertragung geschützt? | G46: Observation | H46: Verträge werden unverschlüsselt versendet auch andere “vertrauliche”? Dokumente werden versendet. Was machen wir nach dem Portal. sobald die Daten bei uns sind die aus dem B2B Kundenportal kommen. Lösungsvorschlag: Trainieren und packen / verschlüsseln Wenn der Kunde uns vertrauliche informationen zuschickt müssen wir dies auch in unserer Lieferkette berücksichtigen. wie stellen wir das sicher? Werden Gehaltszettel per email versendet, wie läuft das? Auditfrage: MA hat vertrauliche Vertragsdokument vom OEM, wie geht er damit im Datenaustausch um? -> Zip + Pswd und dann wieder Upload - Training an MA: Mit welchen klassifizierten Dokumenten muss das so gemacht werden? (Thema: Klassifizierung) -> SK PDF Passwort immer das Gleiche. | I46: 3 | J46: 3 | K46: =IF(AND(ISNUMBER(I46),ISNUMBER(J46)),J46-I46,"") -> 0 | L46: Tipp vom Auditor: Zippen und Verschlüsseln als Anweisung im Workflow (!) Windows 11 kann zwar zippen aber nicht verschlüsseln. 7-Zip (in Matrix41 enthalten !) -> ausrollen für alles User ! Patrick G. hat mit Sascha P. gesprochen: SW Asset Mgmt. müssen wir eine Zusatzlizenz erwerben (Angebotanfrage über S. Pulver) | M46: Umsetzungsgegenstand: Standardisierung verschlüsselter Datenübertragung für vertrauliche Dokumente (7-Zip + Passwort) unternehmensweit, inkl. Trainingsmodul für klassifizierungsabhängige Handhabung. Prozessbezug: VDA ISA 5.1.2; ISO 27001 A.8.20, A.8.24. Workflow Items: 1. 7-Zip-Roll-out auf alle Clients via Matrix42 (Owner: IT). 2. Lizenz-Klärung (Angebot S. Pulver, SW Asset Mgmt.). 3. STD 'Sichere Dateiübertragung' mit Beispielen (Owner: ISB). 4. Trainingsmodul: Klassifizierung → Methode. 5. SK: einheitliches PDF-Passwort beenden, individualisierte Passwörter. Nachweis: SW-Inventory, STD, Trainingsnachweis, Audit-Demo-Use-Case (OEM-Vertragsversand). Abhängigkeiten (Detail s. Spalte N): → baut auf F-027 + F-001; treibt F-014/F-043 | N46: Vorgelagert: - Row 45 / F-027 / 5.1.1 (Kryptografie-Rahmen) - Row 9 / F-001 / 1.1.1 (Klassifikation) Nachgelagert: - Row 32 / F-014 / 1.6.2 (OEM-Kommunikation) - Row 61 / F-043 / 6.1.2 (NDA-Versand) Querverweise: - Row 37 / F-019 / 2.1.4 (Reise-Verschlüsselung) | O46: Policy Framework: - Verfahrensanweisung 'Verschlüsselung externer Versand' - Konkretes Tool-Setup: 7-Zip-Pro-Lizenz für AES-256 + automatisierte Anwendung - Alternative: M365 Information Protection / Sensitivity Labels Standards: - ISO/IEC 27001:2022 A.8.24 - BSI TR-02102 (zulässige Algorithmen) - VDA ISA 6.0.3 Kap. 5.1.2 Weitere Empfehlungen: - Lizenz 7-Zip Pro / professionelle Tool-Wahl klären (Sascha Pulver Open Point) - Schulung 'Mail mit Anlage richtig versenden' (TTT-Modul) - DLP-Regel: Vertraulich/Strictly Confidential → automatisch Verschlüsselung erzwingen | P46: IT, OT, ISB | Q46: Alle | R46: Niedrig | S46: Offen | W46: 1
A47: F-029 | B47: Information Security | C47: IT(OT) Security / Cyber Security | D47: 5.2.1 | E47: To what extent are changes managed? | F47: Inwieweit werden Veränderungen verwaltet? | G47: Major NC | H47: Werden Patches bezüglich Auswirkungen auf Sicherheit geprüft? Auch für OT? Wie ist der Changemanagment Prozess beschrieben? Gibt es ein formales Genehmigungsverfahren. Ab wann ist etwas ein change? Gibt es ein Notfallverfahren falls changes nicht funktioniert haben. Ab wann ist es kein change sondern ein Projekt indem dann der eigentlich Change Projektbestandteil wird. Wie werden Changes im IT und OT Bereich behandelt und umgesetzt? ITILv3/v4 und ITSM für Change Mgmt. und CAB bzw. Change Authority Teil des ISW (ISW dafür im Gremiensteckbrief anpassen), Umsetzung für OT im Change Mgmt. muss noch erfolgen. Was ist ein Change mit entspr. Auswirkung (e.g. Facility und phys. Sicherheit) Gehnemigungsverfahren ist Teil des ISW. | I47: 1 | J47: 3 | K47: =IF(AND(ISNUMBER(I47),ISNUMBER(J47)),J47-I47,"") -> 2 | L47: OT Berücksichtigung ! Change Mgmt integriert in ISW Antrag -> ISB -> Aufbau Change Mgmt. Liste -> Besprechung und Approval OKA/Rejection/OK im ISW Projektspezifische Change extra Gremiensteckbrief Very High Avail: + Compliance with the information security requirements is verified during and after the changes are applied. (C, I, A) | M47: Umsetzungsgegenstand: Durchgängiges Change Management (ITIL-/ITSM-orientiert) für IT und OT mit formaler Genehmigung (CAB / Change Authority im ISW), Notfall-Change-Verfahren, Patch-Security-Impact-Bewertung und Post-Change-Compliance-Verifikation (Very High Availability). Prozessbezug: VDA ISA 5.2.1; ISO 27001 A.8.32. Workflow Items: 1. RL Change Mgmt. (Owner: ISB + IT + OT-Lead). 2. ISW-Antragsprozess als CAB-Funktion etablieren; OT-Repräsentant im ISW. 3. Gremiensteckbrief ISW aktualisieren. 4. Change-Liste mit Approval/Reject-Status. 5. Notfall-Change-Verfahren mit nachträglichem Approval. 6. Patch-Security-Impact-Check vor Deployment. 7. Post-Change-Compliance-Verifikation (C, I, A). Nachweis: RL, ISW-Protokolle, Change-Liste, Verifikations-Reports. Abhängigkeiten (Detail s. Spalte N): → Major NC + Krit. Prio; baut auf F-009/F-010/F-033; treibt F-030/F-032/F-038 | N47: Vorgelagert: - Row 26 / F-009 / 1.3.4 (SW-Review) - Row 28 / F-010 / 1.4.1 (Risiko-Mgmt) - Row 51 / F-033 / 5.2.5 (Vulnerability-Eingangsgröße) Nachgelagert: - Row 48 / F-030 / 5.2.2 (Dev/Test/Prod-Trennung) - Row 50 / F-032 / 5.2.4 (Change-Logs) - Row 56 / F-038 / 5.3.1 (IS in neuen Systemen) Querverweise: - Row 42 / F-024 / 4.1.2 (MFA bei Change-Approval) - Row 44 / F-026 / 4.2.1 (PAM für Changes) | O47: Policy Framework: - RL Change Management (IT + OT separat dokumentiert) - CAB-Geschäftsordnung mit ISW (Information Security Workgroup) als Stimmrecht - Standard / Normal / Emergency Change-Workflows Standards: - ISO/IEC 27001:2022 A.8.32 - ITIL 4 Change Enablement - IEC 62443-2-1 SP.05 (OT-Change-Mgmt) - VDA ISA 6.0.3 Kap. 5.2.1 Weitere Empfehlungen: - KRITISCHE Priorität: CAB-Doku + ISW-Stimmrecht vor AL3-Audit - Change-Risk-Assessment-Template (Pflicht für ≥ Normal Changes) - Patch-Bewertung mit IS-Auswirkung explizit (kein 'Standard-Pass-Through') - OT-Change-Window-Planung mit Produktion abgestimmt | P47: IT, OT, ISB | Q47: DE/SK/PL | R47: Kritisch | S47: Offen | W47: 1
... A63: F-045 | B63: Information Security | C63: Compliance | D63: 7.1.2 | E63: To what extent is the protection of personally identifiable data considered when implementing information security? | F63: Inwieweit wird der Schutz personenbezogener Daten bei der Implementierung der Informationssicherheit berücksichtigt? | G63: Minor NC | H63: Auch hier auf die Länder runterbrechen. Selbst wenn wir einn externen DSB haben brauchen wir lokale verantwortliche. Diese müssen definiert sein und wissen wo sie sich bei welchen Fällen melden können. Manchmal sind auch lokale Behörden zu informieren, dies muss auch in die Beschreibung. Die info muss an alle raus, jeder muss wissen an wen er sich bei was wenden muss. Globaler DPO für alle pan-EU Regionen analog GPDR Prozess und Meldewesen für Data Breach etc. Policies in SK und PL und der Prozess für Verantwortlichkeiten. Wenn Darstellungen fehlen, dann Level 2 | I63: 2 | J63: 3 | K63: =IF(AND(ISNUMBER(I63),ISNUMBER(J63)),J63-I63,"") -> 1 | L63: Bestellung DSB in QBD.net ablegen. Lokale int. DSOs Policy Datenschutz noch in SK, PL und SP überführen (Anmerkung Mark Lütz: ggfs. sollten wir die RL Videoüberwachung mit den nationalen Ausprägungen noch in den gleichen Data Privacy Prozessbereich überführen inkl. der Standards (liegen in allen Sprachen vor auch MX/IN). Hinweis: Etablierung einer Vorgabe nach DSGVO/EU GPDR für die MA Daten fehlt aktuell noch. (Ist nicht im HR Prozess verdrahtet) | M63: Umsetzungsgegenstand: Länderspezifische Datenschutz-Governance mit globalem DPO und lokalen Datenschutzkoordinatoren (DSO) für SK/PL/SP; Übersetzung der Datenschutz- und Videoüberwachungs-RL; HR-DSGVO-Vorgabe für MA-Daten. Prozessbezug: VDA ISA 7.1.2; DSGVO Art. 24, 28, 33–34, 37. Workflow Items: 1. Bestellungsdokumentation DPO in QBD.net (Owner: ISB + Legal). 2. Benennung lokaler DSOs (SK / PL / SP). 3. Übersetzung Datenschutz-RL und Videoüberwachungs-RL je Land (auch MX/IN). 4. HR-DSGVO-Modul für Mitarbeiterdaten. 5. Data-Breach-Meldewege je Land + zuständige Aufsichtsbehörden. Nachweis: Bestellungsurkunde, DSO-Liste, übersetzte RL, Meldewege. Abhängigkeiten (Detail s. Spalte N): → baut auf F-016/F-044/F-032; länderspezifische Umsetzung DE/AT/SK/PL | N63: Vorgelagert: - Row 34 / F-016 / 2.1.1 (HR-Datenschutz) - Row 62 / F-044 / 7.1.1 (Compliance-Rahmen) - Row 50 / F-032 / 5.2.4 (Logging-Datenschutz) Nachgelagert: - keine (länderspezifischer Endpunkt) Querverweise: - Row 61 / F-043 / 6.1.2 (AV-Verträge gem. Art. 28 DSGVO) - Row 31 / F-013 / 1.6.1 (Datenschutzvorfälle Art. 33/34) | O63: Policy Framework: - Datenschutz-Mgmt-System (DSMS) je Standort - Verarbeitungsverzeichnis je Werk (Art. 30 DSGVO) - AV-Vertragsvorlagen je Lieferant - DSFA-Prozess (Datenschutz-Folgenabschätzung) Standards: - ISO/IEC 27701:2019 (PIMS) - ISO/IEC 27001:2022 A.5.34 - VDA ISA 6.0.3 Kap. 7.1.2 Regulatorisch: - DSGVO/GDPR (alle 4 Länder) - DE: BDSG-neu - AT: DSG - SK: Zákon č. 18/2018 Z. z. - PL: Ustawa o ochronie danych osobowych Weitere Empfehlungen: - Lokale Datenschutzbeauftragte (DSO) je Land mit aktiver Funktion - Cross-Border-Datentransfer dokumentieren (Art. 44 ff. DSGVO) - Schulung Datenschutz als verpflichtendes TTT-Modul | P63: GL, Legal, ISB, DSB und Plants, inkl. Lokationen DE/AT, MX/IN | Q63: Alle | R63: Mittel | S63: Offen | W63: 1

Sheet Dashboard
A1: TISAX Finding Dashboard
A3: Kennzahl | B3: Formel | C3: Wert
A4: Gesamtanzahl Kontrollen | B4: COUNTA('TISAX Finding Register'!A4:A82) | C4: =COUNTA('TISAX Finding Register'!A3:A63) -> 61
A5: Findings erfasst (mit Typ) | B5: COUNTIF('TISAX Finding Register'!F4:F82,"<>") | C5: =COUNTIF('TISAX Finding Register'!G3:G64,"<>") -> 60
A6: Major Non-Conformities | B6: COUNTIF('TISAX Finding Register'!F4:F82,"Major NC") | C6: =COUNTIF('TISAX Finding Register'!G3:G64,"Major NC") -> 13
A7: Minor Non-Conformities | B7: COUNTIF('TISAX Finding Register'!F4:F82,"Minor NC") | C7: =COUNTIF('TISAX Finding Register'!G3:G64,"Minor NC") -> 32
A8: Observations | B8: COUNTIF('TISAX Finding Register'!F4:F82,"Observation") | C8: =COUNTIF('TISAX Finding Register'!G3:G64,"Observation") -> 15
A9: OFIs | B9: COUNTIF('TISAX Finding Register'!F4:F82,"OFI") | C9: =COUNTIF('TISAX Finding Register'!G3:G64,"OFI") -> 0
A10: Status: Offen | B10: COUNTIF('TISAX Finding Register'!O4:O82,"Offen") | C10: =COUNTIF('TISAX Finding Register'!Q3:Q63,"Offen") -> 0
A11: Status: In Bearbeitung | B11: COUNTIF('TISAX Finding Register'!O4:O82,"In Bearbeitung") | C11: =COUNTIF('TISAX Finding Register'!Q3:Q63,"In Bearbeitung") -> 0
A12: Status: Umgesetzt | B12: COUNTIF('TISAX Finding Register'!O4:O82,"Umgesetzt") | C12: =COUNTIF('TISAX Finding Register'!Q3:Q63,"Umgesetzt") -> 0
A13: Status: Verifiziert | B13: COUNTIF('TISAX Finding Register'!O4:O82,"Verifiziert") | C13: =COUNTIF('TISAX Finding Register'!Q3:Q63,"Verifiziert") -> 0
A14: Priorität: Kritisch | B14: COUNTIF('TISAX Finding Register'!N4:N82,"Kritisch") | C14: =COUNTIF('TISAX Finding Register'!P3:P63,"Kritisch") -> 0
A15: Priorität: Hoch | B15: COUNTIF('TISAX Finding Register'!N4:N82,"Hoch") | C15: =COUNTIF('TISAX Finding Register'!P3:P63,"Hoch") -> 0
A16: Standort DE | B16: COUNTIF('TISAX Finding Register'!M4:M82,"DE") | C16: =COUNTIF('TISAX Finding Register'!O3:O63,"DE") -> 0
A17: Standort AT | B17: COUNTIF('TISAX Finding Register'!M4:M82,"AT") | C17: =COUNTIF('TISAX Finding Register'!O3:O63,"AT") -> 0
A18: Standort SK | B18: COUNTIF('TISAX Finding Register'!M4:M82,"SK") | C18: =COUNTIF('TISAX Finding Register'!O3:O63,"SK") -> 0
A19: Standort PL | B19: COUNTIF('TISAX Finding Register'!M4:M82,"PL") | C19: =COUNTIF('TISAX Finding Register'!O3:O63,"PL") -> 0

Sheet Anleitung
A1: TISAX Finding Register — Importanleitung für MS Lists
A3: 1. IMPORT IN MICROSOFT LISTS
A4: • Öffne Microsoft Lists (über Teams oder lists.microsoft.com)
A5: • Klicke 'Neue Liste' → 'Aus Excel'
A6: • Wähle diese Datei und das Sheet 'TISAX Finding Register'
A7: • Prüfe die Spaltentypen (Text, Choice, Number, Date)
A8: • Choice-Spalten: Finding-Typ, Standort, Priorität, Status mit Dropdown
A10: 2. SPALTEN-KONFIGURATION IN LISTS
A11: • Finding-ID: Einzelne Textzeile
A12: • ISA Modul / Kapitel / Kontrollfrage: Mehrzeiliger Text
A13: • Finding-Typ: Choice (Major NC, Minor NC, Observation, OFI, Conformity)
A14: • Reifegrad IST / SOLL: Number (0-5)
... A47: Basierend auf VDA ISA 6.0.3 — Stand März 2026
